Workbook

Sheet sales_pipeline
A1: opportunity_id | B1: Opportunity Type | C1: sales_agent | D1: sales_agent_id | E1: manager | F1: regional_office | G1: product | H1: series | I1: account | J1: sector | K1: account_tier | L1: deal_stage | M1: Win/Loss Reason | N1: Competitor | O1: engage_date | P1: close_date | Q1: price_per_unit | R1: Units Sold | S1: closing_price
A2: 1C1I7A6R | B2: Expansion | C2: Moses Frase | D2: =_xlfn.XLOOKUP(C2,sales_teams!A:A,sales_teams!B:B,"") -> C62195 | E2: =_xlfn.XLOOKUP(C2,sales_teams!A:A,sales_teams!C:C,"") -> Dustin Brinkmann | F2: =_xlfn.XLOOKUP(C2,sales_teams!A:A,sales_teams!D:D,"") -> Central | G2: GTX Plus Basic | H2: =_xlfn.XLOOKUP(G2,products!A:A,products!B:B,"") -> GTX | I2: Cancity | J2: =_xlfn.XLOOKUP(I2,accounts!A:A,accounts!B:B,"") -> retail | K2: =_xlfn.XLOOKUP(I2,accounts!A:A,accounts!F:F,"") -> Mid-Market | L2: Won | M2: Executive Relationship | N2: Ivy Green-Tech | O2: 42663 | P2: 42795 | Q2: =_xlfn.XLOOKUP(G2,products!A:A,products!C:C,"") -> 1096 | R2: 50 | S2: =Q2*R2 -> 54800
A3: Z063OYW0 | B3: Acquisition | C3: Darcel Schlecht | D3: =_xlfn.XLOOKUP(C3,sales_teams!A:A,sales_teams!B:B,"") -> C486814 | E3: =_xlfn.XLOOKUP(C3,sales_teams!A:A,sales_teams!C:C,"") -> Melvin Marxen | F3: =_xlfn.XLOOKUP(C3,sales_teams!A:A,sales_teams!D:D,"") -> Central | G3: GTX Pro | H3: =_xlfn.XLOOKUP(G3,products!A:A,products!B:B,"") -> GTX | I3: Isdom | J3: =_xlfn.XLOOKUP(I3,accounts!A:A,accounts!B:B,"") -> medical | K3: =_xlfn.XLOOKUP(I3,accounts!A:A,accounts!F:F,"") -> Mid-Market | L3: Won | M3: Advanced Technology | N3: Ivy Green-Tech | O3: 42668 | P3: 42805 | Q3: =_xlfn.XLOOKUP(G3,products!A:A,products!C:C,"") -> 4821 | R3: 37 | S3: =Q3*R3 -> 178377
A4: EC4QE1BX | B4: Expansion | C4: Darcel Schlecht | D4: =_xlfn.XLOOKUP(C4,sales_teams!A:A,sales_teams!B:B,"") -> C486814 | E4: =_xlfn.XLOOKUP(C4,sales_teams!A:A,sales_teams!C:C,"") -> Melvin Marxen | F4: =_xlfn.XLOOKUP(C4,sales_teams!A:A,sales_teams!D:D,"") -> Central | G4: MG Special | H4: =_xlfn.XLOOKUP(G4,products!A:A,products!B:B,"") -> MG | I4: Cancity | J4: =_xlfn.XLOOKUP(I4,accounts!A:A,accounts!B:B,"") -> retail | K4: =_xlfn.XLOOKUP(I4,accounts!A:A,accounts!F:F,"") -> Mid-Market | L4: Won | M4: Brand Uniqueness | N4: Falconia Enterprises | O4: 42668 | P4: 42801 | Q4: =_xlfn.XLOOKUP(G4,products!A:A,products!C:C,"") -> 55 | R4: 8 | S4: =Q4*R4 -> 440
A5: MV1LWRNH | B5: Expansion | C5: Moses Frase | D5: =_xlfn.XLOOKUP(C5,sales_teams!A:A,sales_teams!B:B,"") -> C62195 | E5: =_xlfn.XLOOKUP(C5,sales_teams!A:A,sales_teams!C:C,"") -> Dustin Brinkmann | F5: =_xlfn.XLOOKUP(C5,sales_teams!A:A,sales_teams!D:D,"") -> Central | G5: GTX Basic | H5: =_xlfn.XLOOKUP(G5,products!A:A,products!B:B,"") -> GTX | I5: Codehow | J5: =_xlfn.XLOOKUP(I5,accounts!A:A,accounts!B:B,"") -> software | K5: =_xlfn.XLOOKUP(I5,accounts!A:A,accounts!F:F,"") -> Mid-Market | L5: Won | M5: Advanced Technology | N5: Ivy Green-Tech | O5: 42668 | P5: 42803 | Q5: =_xlfn.XLOOKUP(G5,products!A:A,products!C:C,"") -> 550 | R5: 32 | S5: =Q5*R5 -> 17600
A6: PE84CX4O | B6: Retention | C6: Zane Levy | D6: =_xlfn.XLOOKUP(C6,sales_teams!A:A,sales_teams!B:B,"") -> W202814 | E6: =_xlfn.XLOOKUP(C6,sales_teams!A:A,sales_teams!C:C,"") -> Summer Sewald | F6: =_xlfn.XLOOKUP(C6,sales_teams!A:A,sales_teams!D:D,"") -> West | G6: GTX Basic | H6: =_xlfn.XLOOKUP(G6,products!A:A,products!B:B,"") -> GTX | I6: Hatfan | J6: =_xlfn.XLOOKUP(I6,accounts!A:A,accounts!B:B,"") -> services | K6: =_xlfn.XLOOKUP(I6,accounts!A:A,accounts!F:F,"") -> Mid-Market | L6: Won | M6: Product Superiority | N6: Cobblepot Exports | O6: 42668 | P6: 42796 | Q6: =_xlfn.XLOOKUP(G6,products!A:A,products!C:C,"") -> 550 | R6: 5 | S6: =Q6*R6 -> 2750
A7: ZNBS69V1 | B7: Expansion | C7: Anna Snelling | D7: =_xlfn.XLOOKUP(C7,sales_teams!A:A,sales_teams!B:B,"") -> C265891 | E7: =_xlfn.XLOOKUP(C7,sales_teams!A:A,sales_teams!C:C,"") -> Dustin Brinkmann | F7: =_xlfn.XLOOKUP(C7,sales_teams!A:A,sales_teams!D:D,"") -> Central | G7: MG Special | H7: =_xlfn.XLOOKUP(G7,products!A:A,products!B:B,"") -> MG | I7: Ron-tech | J7: =_xlfn.XLOOKUP(I7,accounts!A:A,accounts!B:B,"") -> medical | K7: =_xlfn.XLOOKUP(I7,accounts!A:A,accounts!F:F,"") -> Enterprise | L7: Won | M7: Strategic Timing | N7: Cobblepot Exports | O7: 42672 | P7: 42795 | Q7: =_xlfn.XLOOKUP(G7,products!A:A,products!C:C,"") -> 55 | R7: 36 | S7: =Q7*R7 -> 1980
A8: 9ME3374G | B8: Retention | C8: Vicki Laflamme | D8: =_xlfn.XLOOKUP(C8,sales_teams!A:A,sales_teams!B:B,"") -> W975078 | E8: =_xlfn.XLOOKUP(C8,sales_teams!A:A,sales_teams!C:C,"") -> Celia Rouche | F8: =_xlfn.XLOOKUP(C8,sales_teams!A:A,sales_teams!D:D,"") -> West | G8: MG Special | H8: =_xlfn.XLOOKUP(G8,products!A:A,products!B:B,"") -> MG | I8: J-Texon | J8: =_xlfn.XLOOKUP(I8,accounts!A:A,accounts!B:B,"") -> retail | K8: =_xlfn.XLOOKUP(I8,accounts!A:A,accounts!F:F,"") -> Mid-Market | L8: Won | M8: Brand Uniqueness | N8: Enigma Analytics | O8: 42673 | P8: 42796 | Q8: =_xlfn.XLOOKUP(G8,products!A:A,products!C:C,"") -> 55 | R8: 27 | S8: =Q8*R8 -> 1485
A9: 7GN8Q4LL | B9: Diversification | C9: Markita Hansen | D9: =_xlfn.XLOOKUP(C9,sales_teams!A:A,sales_teams!B:B,"") -> W337844 | E9: =_xlfn.XLOOKUP(C9,sales_teams!A:A,sales_teams!C:C,"") -> Celia Rouche | F9: =_xlfn.XLOOKUP(C9,sales_teams!A:A,sales_teams!D:D,"") -> West | G9: GTX Basic | H9: =_xlfn.XLOOKUP(G9,products!A:A,products!B:B,"") -> GTX | I9: Cheers | J9: =_xlfn.XLOOKUP(I9,accounts!A:A,accounts!B:B,"") -> entertainment | K9: =_xlfn.XLOOKUP(I9,accounts!A:A,accounts!F:F,"") -> Enterprise | L9: Won | M9: Executive Relationship | N9: Falconia Enterprises | O9: 42675 | P9: 42801 | Q9: =_xlfn.XLOOKUP(G9,products!A:A,products!C:C,"") -> 550 | R9: 2 | S9: =Q9*R9 -> 1100
A10: OLK9LKZB | B10: Acquisition | C10: Niesha Huffines | D10: =_xlfn.XLOOKUP(C10,sales_teams!A:A,sales_teams!B:B,"") -> C961860 | E10: =_xlfn.XLOOKUP(C10,sales_teams!A:A,sales_teams!C:C,"") -> Melvin Marxen | F10: =_xlfn.XLOOKUP(C10,sales_teams!A:A,sales_teams!D:D,"") -> Central | G10: GTX Plus Basic | H10: =_xlfn.XLOOKUP(G10,products!A:A,products!B:B,"") -> GTX | I10: Zumgoity | J10: =_xlfn.XLOOKUP(I10,accounts!A:A,accounts!B:B,"") -> medical | K10: =_xlfn.XLOOKUP(I10,accounts!A:A,accounts!F:F,"") -> Mid-Market | L10: Won | M10: Advanced Technology | N10: Cobblepot Exports | O10: 42675 | P10: 42797 | Q10: =_xlfn.XLOOKUP(G10,products!A:A,products!C:C,"") -> 1096 | R10: 46 | S10: =Q10*R10 -> 50416
A11: HAXMC4IX | B11: Acquisition | C11: James Ascencio | D11: =_xlfn.XLOOKUP(C11,sales_teams!A:A,sales_teams!B:B,"") -> W249222 | E11: =_xlfn.XLOOKUP(C11,sales_teams!A:A,sales_teams!C:C,"") -> Summer Sewald | F11: =_xlfn.XLOOKUP(C11,sales_teams!A:A,sales_teams!D:D,"") -> West | G11: MG Advanced | H11: =_xlfn.XLOOKUP(G11,products!A:A,products!B:B,"") -> MG | J11: =_xlfn.XLOOKUP(I11,accounts!A:A,accounts!B:B,"") -> 0 | K11: =_xlfn.XLOOKUP(I11,accounts!A:A,accounts!F:F,"") -> 0 | L11: Engaging | N11: TBD | O11: 42677 | Q11: =_xlfn.XLOOKUP(G11,products!A:A,products!C:C,"") -> 3393 | R11: 33 | S11: =Q11*R11 -> 111969
A12: NL3JZH1Z | B12: Retention | C12: Anna Snelling | D12: =_xlfn.XLOOKUP(C12,sales_teams!A:A,sales_teams!B:B,"") -> C265891 | E12: =_xlfn.XLOOKUP(C12,sales_teams!A:A,sales_teams!C:C,"") -> Dustin Brinkmann | F12: =_xlfn.XLOOKUP(C12,sales_teams!A:A,sales_teams!D:D,"") -> Central | G12: MG Special | H12: =_xlfn.XLOOKUP(G12,products!A:A,products!B:B,"") -> MG | I12: Bioholding | J12: =_xlfn.XLOOKUP(I12,accounts!A:A,accounts!B:B,"") -> medical | K12: =_xlfn.XLOOKUP(I12,accounts!A:A,accounts!F:F,"") -> Mid-Market | L12: Won | M12: Brand Uniqueness | N12: Cobblepot Exports | O12: 42678 | P12: 42804 | Q12: =_xlfn.XLOOKUP(G12,products!A:A,products!C:C,"") -> 55 | R12: 40 | S12: =Q12*R12 -> 2200
A13: KWVA7VR1 | B13: Expansion | C13: Gladys Colclough | D13: =_xlfn.XLOOKUP(C13,sales_teams!A:A,sales_teams!B:B,"") -> C130664 | E13: =_xlfn.XLOOKUP(C13,sales_teams!A:A,sales_teams!C:C,"") -> Melvin Marxen | F13: =_xlfn.XLOOKUP(C13,sales_teams!A:A,sales_teams!D:D,"") -> Central | G13: GTX Pro | H13: =_xlfn.XLOOKUP(G13,products!A:A,products!B:B,"") -> GTX | I13: Genco Pura Olive Oil Company | J13: =_xlfn.XLOOKUP(I13,accounts!A:A,accounts!B:B,"") -> retail | K13: =_xlfn.XLOOKUP(I13,accounts!A:A,accounts!F:F,"") -> Mid-Market | L13: Lost | M13: Budget Misalignment | N13: Cobblepot Exports | O13: 42678 | P13: 42812 | Q13: =_xlfn.XLOOKUP(G13,products!A:A,products!C:C,"") -> 4821 | R13: 25 | S13: =Q13*R13 -> 120525
A14: S8DX3XOU | B14: Retention | C14: James Ascencio | D14: =_xlfn.XLOOKUP(C14,sales_teams!A:A,sales_teams!B:B,"") -> W249222 | E14: =_xlfn.XLOOKUP(C14,sales_teams!A:A,sales_teams!C:C,"") -> Summer Sewald | F14: =_xlfn.XLOOKUP(C14,sales_teams!A:A,sales_teams!D:D,"") -> West | G14: GTX Plus Pro | H14: =_xlfn.XLOOKUP(G14,products!A:A,products!B:B,"") -> GTX | I14: Sunnamplex | J14: =_xlfn.XLOOKUP(I14,accounts!A:A,accounts!B:B,"") -> marketing | K14: =_xlfn.XLOOKUP(I14,accounts!A:A,accounts!F:F,"") -> Mid-Market | L14: Won | M14: Executive Relationship | N14: Cobblepot Exports | O14: 42678 | P14: 42804 | Q14: =_xlfn.XLOOKUP(G14,products!A:A,products!C:C,"") -> 5482 | R14: 12 | S14: =Q14*R14 -> 65784
A15: ENB2XD8G | B15: Acquisition | C15: Maureen Marcano | D15: =_xlfn.XLOOKUP(C15,sales_teams!A:A,sales_teams!B:B,"") -> W960943 | E15: =_xlfn.XLOOKUP(C15,sales_teams!A:A,sales_teams!C:C,"") -> Summer Sewald | F15: =_xlfn.XLOOKUP(C15,sales_teams!A:A,sales_teams!D:D,"") -> West | G15: GTX Plus Pro | H15: =_xlfn.XLOOKUP(G15,products!A:A,products!B:B,"") -> GTX | I15: Sonron | J15: =_xlfn.XLOOKUP(I15,accounts!A:A,accounts!B:B,"") -> telecommunications | K15: =_xlfn.XLOOKUP(I15,accounts!A:A,accounts!F:F,"") -> Enterprise | L15: Won | M15: Strategic Timing | N15: Cobblepot Exports | O15: 42678 | P15: 42800 | Q15: =_xlfn.XLOOKUP(G15,products!A:A,products!C:C,"") -> 5482 | R15: 47 | S15: =Q15*R15 -> 257654
A16: 09YE9QOV | B16: Acquisition | C16: Hayden Neloms | D16: =_xlfn.XLOOKUP(C16,sales_teams!A:A,sales_teams!B:B,"") -> W815792 | E16: =_xlfn.XLOOKUP(C16,sales_teams!A:A,sales_teams!C:C,"") -> Celia Rouche | F16: =_xlfn.XLOOKUP(C16,sales_teams!A:A,sales_teams!D:D,"") -> West | G16: MG Advanced | H16: =_xlfn.XLOOKUP(G16,products!A:A,products!B:B,"") -> MG | I16: Finjob | J16: =_xlfn.XLOOKUP(I16,accounts!A:A,accounts!B:B,"") -> employment | K16: =_xlfn.XLOOKUP(I16,accounts!A:A,accounts!F:F,"") -> Mid-Market | L16: Won | M16: Product Superiority | N16: Enigma Analytics | O16: 42679 | P16: 42805 | Q16: =_xlfn.XLOOKUP(G16,products!A:A,products!C:C,"") -> 3393 | R16: 32 | S16: =Q16*R16 -> 108576
A17: 3F5MZNEH | B17: Diversification | C17: Rosalina Dieter | D17: =_xlfn.XLOOKUP(C17,sales_teams!A:A,sales_teams!B:B,"") -> W100826 | E17: =_xlfn.XLOOKUP(C17,sales_teams!A:A,sales_teams!C:C,"") -> Celia Rouche | F17: =_xlfn.XLOOKUP(C17,sales_teams!A:A,sales_teams!D:D,"") -> West | G17: MG Special | H17: =_xlfn.XLOOKUP(G17,products!A:A,products!B:B,"") -> MG | I17: Sonron | J17: =_xlfn.XLOOKUP(I17,accounts!A:A,accounts!B:B,"") -> telecommunications | K17: =_xlfn.XLOOKUP(I17,accounts!A:A,accounts!F:F,"") -> Enterprise | L17: Lost | M17: Strategic Pivot | N17: Enigma Analytics | O17: 42679 | P17: 42797 | Q17: =_xlfn.XLOOKUP(G17,products!A:A,products!C:C,"") -> 55 | R17: 11 | S17: =Q17*R17 -> 605
A18: M6WEJXC0 | B18: Retention | C18: Rosalina Dieter | D18: =_xlfn.XLOOKUP(C18,sales_teams!A:A,sales_teams!B:B,"") -> W100826 | E18: =_xlfn.XLOOKUP(C18,sales_teams!A:A,sales_teams!C:C,"") -> Celia Rouche | F18: =_xlfn.XLOOKUP(C18,sales_teams!A:A,sales_teams!D:D,"") -> West | G18: MG Advanced | H18: =_xlfn.XLOOKUP(G18,products!A:A,products!B:B,"") -> MG | I18: Scotfind | J18: =_xlfn.XLOOKUP(I18,accounts!A:A,accounts!B:B,"") -> software | K18: =_xlfn.XLOOKUP(I18,accounts!A:A,accounts!F:F,"") -> Enterprise | L18: Won | M18: Strategic Timing | N18: Cobblepot Exports | O18: 42679 | P18: 42800 | Q18: =_xlfn.XLOOKUP(G18,products!A:A,products!C:C,"") -> 3393 | R18: 37 | S18: =Q18*R18 -> 125541
A19: 6PTR7VBR | B19: Diversification | C19: Versie Hillebrand | D19: =_xlfn.XLOOKUP(C19,sales_teams!A:A,sales_teams!B:B,"") -> C234829 | E19: =_xlfn.XLOOKUP(C19,sales_teams!A:A,sales_teams!C:C,"") -> Dustin Brinkmann | F19: =_xlfn.XLOOKUP(C19,sales_teams!A:A,sales_teams!D:D,"") -> Central | G19: MG Special | H19: =_xlfn.XLOOKUP(G19,products!A:A,products!B:B,"") -> MG | I19: Treequote | J19: =_xlfn.XLOOKUP(I19,accounts!A:A,accounts!B:B,"") -> telecommunications | K19: =_xlfn.XLOOKUP(I19,accounts!A:A,accounts!F:F,"") -> Enterprise | L19: Won | M19: Brand Uniqueness | N19: Cobblepot Exports | O19: 42680 | P19: 42799 | Q19: =_xlfn.XLOOKUP(G19,products!A:A,products!C:C,"") -> 55 | R19: 35 | S19: =Q19*R19 -> 1925
A20: 902REDPA | B20: Retention | C20: Daniell Hammack | D20: =_xlfn.XLOOKUP(C20,sales_teams!A:A,sales_teams!B:B,"") -> E372575 | E20: =_xlfn.XLOOKUP(C20,sales_teams!A:A,sales_teams!C:C,"") -> Rocco Neubert | F20: =_xlfn.XLOOKUP(C20,sales_teams!A:A,sales_teams!D:D,"") -> East | G20: GTX Pro | H20: =_xlfn.XLOOKUP(G20,products!A:A,products!B:B,"") -> GTX | I20: Xx-zobam | J20: =_xlfn.XLOOKUP(I20,accounts!A:A,accounts!B:B,"") -> entertainment | K20: =_xlfn.XLOOKUP(I20,accounts!A:A,accounts!F:F,"") -> Enterprise | L20: Lost | M20: Strategic Pivot | N20: Enigma Analytics | O20: 42681 | P20: 42803 | Q20: =_xlfn.XLOOKUP(G20,products!A:A,products!C:C,"") -> 4821 | R20: 19 | S20: =Q20*R20 -> 91599
A21: 5J9CMGDV | B21: Acquisition | C21: Elease Gluck | D21: =_xlfn.XLOOKUP(C21,sales_teams!A:A,sales_teams!B:B,"") -> W172727 | E21: =_xlfn.XLOOKUP(C21,sales_teams!A:A,sales_teams!C:C,"") -> Celia Rouche | F21: =_xlfn.XLOOKUP(C21,sales_teams!A:A,sales_teams!D:D,"") -> West | G21: MG Special | H21: =_xlfn.XLOOKUP(G21,products!A:A,products!B:B,"") -> MG | I21: Rantouch | J21: =_xlfn.XLOOKUP(I21,accounts!A:A,accounts!B:B,"") -> telecommunications | K21: =_xlfn.XLOOKUP(I21,accounts!A:A,accounts!F:F,"") -> Mid-Market | L21: Won | M21: Brand Uniqueness | N21: Ivy Green-Tech | O21: 42681 | P21: 42802 | Q21: =_xlfn.XLOOKUP(G21,products!A:A,products!C:C,"") -> 55 | R21: 34 | S21: =Q21*R21 -> 1870
A22: JJXRR8R6 | B22: Expansion | C22: James Ascencio | D22: =_xlfn.XLOOKUP(C22,sales_teams!A:A,sales_teams!B:B,"") -> W249222 | E22: =_xlfn.XLOOKUP(C22,sales_teams!A:A,sales_teams!C:C,"") -> Summer Sewald | F22: =_xlfn.XLOOKUP(C22,sales_teams!A:A,sales_teams!D:D,"") -> West | G22: GTX Plus Pro | H22: =_xlfn.XLOOKUP(G22,products!A:A,products!B:B,"") -> GTX | I22: Fasehatice | J22: =_xlfn.XLOOKUP(I22,accounts!A:A,accounts!B:B,"") -> retail | K22: =_xlfn.XLOOKUP(I22,accounts!A:A,accounts!F:F,"") -> Enterprise | L22: Lost | M22: Budget Misalignment | N22: Enigma Analytics | O22: 42681 | P22: 42811 | Q22: =_xlfn.XLOOKUP(G22,products!A:A,products!C:C,"") -> 5482 | R22: 33 | S22: =Q22*R22 -> 180906
A23: WF4HA5NW | B23: Diversification | C23: Moses Frase | D23: =_xlfn.XLOOKUP(C23,sales_teams!A:A,sales_teams!B:B,"") -> C62195 | E23: =_xlfn.XLOOKUP(C23,sales_teams!A:A,sales_teams!C:C,"") -> Dustin Brinkmann | F23: =_xlfn.XLOOKUP(C23,sales_teams!A:A,sales_teams!D:D,"") -> Central | G23: MG Special | H23: =_xlfn.XLOOKUP(G23,products!A:A,products!B:B,"") -> MG | I23: Ron-tech | J23: =_xlfn.XLOOKUP(I23,accounts!A:A,accounts!B:B,"") -> medical | K23: =_xlfn.XLOOKUP(I23,accounts!A:A,accounts!F:F,"") -> Enterprise | L23: Won | M23: Strategic Timing | N23: Enigma Analytics | O23: 42681 | P23: 42812 | Q23: =_xlfn.XLOOKUP(G23,products!A:A,products!C:C,"") -> 55 | R23: 11 | S23: =Q23*R23 -> 605
... A26: SBCR987L | B26: Retention | C26: Kami Bicknell | D26: =_xlfn.XLOOKUP(C26,sales_teams!A:A,sales_teams!B:B,"") -> W596440 | E26: =_xlfn.XLOOKUP(C26,sales_teams!A:A,sales_teams!C:C,"") -> Summer Sewald | F26: =_xlfn.XLOOKUP(C26,sales_teams!A:A,sales_teams!D:D,"") -> West | G26: GTX Basic | H26: =_xlfn.XLOOKUP(G26,products!A:A,products!B:B,"") -> GTX | I26: Zoomit | J26: =_xlfn.XLOOKUP(I26,accounts!A:A,accounts!B:B,"") -> entertainment | K26: =_xlfn.XLOOKUP(I26,accounts!A:A,accounts!F:F,"") -> SMB | L26: Won | M26: Strategic Timing | N26: Ivy Green-Tech | O26: 42684 | P26: 42817 | Q26: =_xlfn.XLOOKUP(G26,products!A:A,products!C:C,"") -> 550 | R26: 20 | S26: =Q26*R26 -> 11000
A27: UP409DSB | B27: Diversification | C27: Maureen Marcano | D27: =_xlfn.XLOOKUP(C27,sales_teams!A:A,sales_teams!B:B,"") -> W960943 | E27: =_xlfn.XLOOKUP(C27,sales_teams!A:A,sales_teams!C:C,"") -> Summer Sewald | F27: =_xlfn.XLOOKUP(C27,sales_teams!A:A,sales_teams!D:D,"") -> West | G27: MG Advanced | H27: =_xlfn.XLOOKUP(G27,products!A:A,products!B:B,"") -> MG | I27: Ganjaflex | J27: =_xlfn.XLOOKUP(I27,accounts!A:A,accounts!B:B,"") -> retail | K27: =_xlfn.XLOOKUP(I27,accounts!A:A,accounts!F:F,"") -> Enterprise | L27: Engaging | N27: TBD | O27: 42684 | Q27: =_xlfn.XLOOKUP(G27,products!A:A,products!C:C,"") -> 3393 | R27: 48 | S27: =Q27*R27 -> 162864
A28: JSD4APT2 | B28: Expansion | C28: Versie Hillebrand | D28: =_xlfn.XLOOKUP(C28,sales_teams!A:A,sales_teams!B:B,"") -> C234829 | E28: =_xlfn.XLOOKUP(C28,sales_teams!A:A,sales_teams!C:C,"") -> Dustin Brinkmann | F28: =_xlfn.XLOOKUP(C28,sales_teams!A:A,sales_teams!D:D,"") -> Central | G28: MG Special | H28: =_xlfn.XLOOKUP(G28,products!A:A,products!B:B,"") -> MG | I28: Bioholding | J28: =_xlfn.XLOOKUP(I28,accounts!A:A,accounts!B:B,"") -> medical | K28: =_xlfn.XLOOKUP(I28,accounts!A:A,accounts!F:F,"") -> Mid-Market | L28: Won | M28: Executive Relationship | N28: Ivy Green-Tech | O28: 42684 | P28: 42806 | Q28: =_xlfn.XLOOKUP(G28,products!A:A,products!C:C,"") -> 55 | R28: 15 | S28: =Q28*R28 -> 825
A29: AO9Z2D17 | B29: Retention | C29: Violet Mclelland | D29: =_xlfn.XLOOKUP(C29,sales_teams!A:A,sales_teams!B:B,"") -> E152967 | E29: =_xlfn.XLOOKUP(C29,sales_teams!A:A,sales_teams!C:C,"") -> Cara Losch | F29: =_xlfn.XLOOKUP(C29,sales_teams!A:A,sales_teams!D:D,"") -> East | G29: GTX Plus Pro | H29: =_xlfn.XLOOKUP(G29,products!A:A,products!B:B,"") -> GTX | I29: Xx-zobam | J29: =_xlfn.XLOOKUP(I29,accounts!A:A,accounts!B:B,"") -> entertainment | K29: =_xlfn.XLOOKUP(I29,accounts!A:A,accounts!F:F,"") -> Enterprise | L29: Lost | M29: Budget Misalignment | N29: Ivy Green-Tech | O29: 42684 | P29: 42805 | Q29: =_xlfn.XLOOKUP(G29,products!A:A,products!C:C,"") -> 5482 | R29: 46 | S29: =Q29*R29 -> 252172
A30: 5M58DTJK | B30: Retention | C30: Elease Gluck | D30: =_xlfn.XLOOKUP(C30,sales_teams!A:A,sales_teams!B:B,"") -> W172727 | E30: =_xlfn.XLOOKUP(C30,sales_teams!A:A,sales_teams!C:C,"") -> Celia Rouche | F30: =_xlfn.XLOOKUP(C30,sales_teams!A:A,sales_teams!D:D,"") -> West | G30: MG Special | H30: =_xlfn.XLOOKUP(G30,products!A:A,products!B:B,"") -> MG | I30: Cheers | J30: =_xlfn.XLOOKUP(I30,accounts!A:A,accounts!B:B,"") -> entertainment | K30: =_xlfn.XLOOKUP(I30,accounts!A:A,accounts!F:F,"") -> Enterprise | L30: Won | M30: Advanced Technology | N30: Ivy Green-Tech | O30: 42685 | P30: 42799 | Q30: =_xlfn.XLOOKUP(G30,products!A:A,products!C:C,"") -> 55 | R30: 19 | S30: =Q30*R30 -> 1045
A31: KNY1OSAB | B31: Retention | C31: Maureen Marcano | D31: =_xlfn.XLOOKUP(C31,sales_teams!A:A,sales_teams!B:B,"") -> W960943 | E31: =_xlfn.XLOOKUP(C31,sales_teams!A:A,sales_teams!C:C,"") -> Summer Sewald | F31: =_xlfn.XLOOKUP(C31,sales_teams!A:A,sales_teams!D:D,"") -> West | G31: GTX Pro | H31: =_xlfn.XLOOKUP(G31,products!A:A,products!B:B,"") -> GTX | I31: Labdrill | J31: =_xlfn.XLOOKUP(I31,accounts!A:A,accounts!B:B,"") -> medical | K31: =_xlfn.XLOOKUP(I31,accounts!A:A,accounts!F:F,"") -> Enterprise | L31: Won | M31: Strategic Timing | N31: Ivy Green-Tech | O31: 42685 | P31: 42808 | Q31: =_xlfn.XLOOKUP(G31,products!A:A,products!C:C,"") -> 4821 | R31: 12 | S31: =Q31*R31 -> 57852
A32: EAZDUUM9 | B32: Acquisition | C32: Rosie Papadopoulos | D32: =_xlfn.XLOOKUP(C32,sales_teams!A:A,sales_teams!B:B,"") -> E777204 | E32: =_xlfn.XLOOKUP(C32,sales_teams!A:A,sales_teams!C:C,"") -> Cara Losch | F32: =_xlfn.XLOOKUP(C32,sales_teams!A:A,sales_teams!D:D,"") -> East | G32: MG Advanced | H32: =_xlfn.XLOOKUP(G32,products!A:A,products!B:B,"") -> MG | I32: Zotware | J32: =_xlfn.XLOOKUP(I32,accounts!A:A,accounts!B:B,"") -> software | K32: =_xlfn.XLOOKUP(I32,accounts!A:A,accounts!F:F,"") -> Enterprise | L32: Lost | M32: Competitor Selection | N32: Falconia Enterprises | O32: 42685 | P32: 42795 | Q32: =_xlfn.XLOOKUP(G32,products!A:A,products!C:C,"") -> 3393 | R32: 2 | S32: =Q32*R32 -> 6786
A33: 2STUSOFE | B33: Retention | C33: Versie Hillebrand | D33: =_xlfn.XLOOKUP(C33,sales_teams!A:A,sales_teams!B:B,"") -> C234829 | E33: =_xlfn.XLOOKUP(C33,sales_teams!A:A,sales_teams!C:C,"") -> Dustin Brinkmann | F33: =_xlfn.XLOOKUP(C33,sales_teams!A:A,sales_teams!D:D,"") -> Central | G33: MG Special | H33: =_xlfn.XLOOKUP(G33,products!A:A,products!B:B,"") -> MG | I33: dambase | J33: =_xlfn.XLOOKUP(I33,accounts!A:A,accounts!B:B,"") -> marketing | K33: =_xlfn.XLOOKUP(I33,accounts!A:A,accounts!F:F,"") -> Mid-Market | L33: Won | M33: Brand Uniqueness | N33: Falconia Enterprises | O33: 42685 | P33: 42797 | Q33: =_xlfn.XLOOKUP(G33,products!A:A,products!C:C,"") -> 55 | R33: 3 | S33: =Q33*R33 -> 165
A34: JYKM0B00 | B34: Expansion | C34: James Ascencio | D34: =_xlfn.XLOOKUP(C34,sales_teams!A:A,sales_teams!B:B,"") -> W249222 | E34: =_xlfn.XLOOKUP(C34,sales_teams!A:A,sales_teams!C:C,"") -> Summer Sewald | F34: =_xlfn.XLOOKUP(C34,sales_teams!A:A,sales_teams!D:D,"") -> West | G34: GTX Pro | H34: =_xlfn.XLOOKUP(G34,products!A:A,products!B:B,"") -> GTX | I34: Xx-holding | J34: =_xlfn.XLOOKUP(I34,accounts!A:A,accounts!B:B,"") -> finance | K34: =_xlfn.XLOOKUP(I34,accounts!A:A,accounts!F:F,"") -> Enterprise | L34: Won | M34: Executive Relationship | N34: Enigma Analytics | O34: 42686 | P34: 42800 | Q34: =_xlfn.XLOOKUP(G34,products!A:A,products!C:C,"") -> 4821 | R34: 2 | S34: =Q34*R34 -> 9642
A35: KU28360J | B35: Acquisition | C35: Kary Hendrixson | D35: =_xlfn.XLOOKUP(C35,sales_teams!A:A,sales_teams!B:B,"") -> W674591 | E35: =_xlfn.XLOOKUP(C35,sales_teams!A:A,sales_teams!C:C,"") -> Summer Sewald | F35: =_xlfn.XLOOKUP(C35,sales_teams!A:A,sales_teams!D:D,"") -> West | G35: GTX Basic | H35: =_xlfn.XLOOKUP(G35,products!A:A,products!B:B,"") -> GTX | I35: Fasehatice | J35: =_xlfn.XLOOKUP(I35,accounts!A:A,accounts!B:B,"") -> retail | K35: =_xlfn.XLOOKUP(I35,accounts!A:A,accounts!F:F,"") -> Enterprise | L35: Won | M35: Product Superiority | N35: Ivy Green-Tech | O35: 42686 | P35: 42813 | Q35: =_xlfn.XLOOKUP(G35,products!A:A,products!C:C,"") -> 550 | R35: 4 | S35: =Q35*R35 -> 2200
A36: N4SD17JR | B36: Retention | C36: Reed Clapper | D36: =_xlfn.XLOOKUP(C36,sales_teams!A:A,sales_teams!B:B,"") -> E571180 | E36: =_xlfn.XLOOKUP(C36,sales_teams!A:A,sales_teams!C:C,"") -> Rocco Neubert | F36: =_xlfn.XLOOKUP(C36,sales_teams!A:A,sales_teams!D:D,"") -> East | G36: GTX Basic | H36: =_xlfn.XLOOKUP(G36,products!A:A,products!B:B,"") -> GTX | I36: Acme Corporation | J36: =_xlfn.XLOOKUP(I36,accounts!A:A,accounts!B:B,"") -> technolgy | K36: =_xlfn.XLOOKUP(I36,accounts!A:A,accounts!F:F,"") -> Mid-Market | L36: Won | M36: Executive Relationship | N36: Enigma Analytics | O36: 42686 | P36: 42795 | Q36: =_xlfn.XLOOKUP(G36,products!A:A,products!C:C,"") -> 550 | R36: 5 | S36: =Q36*R36 -> 2750
A37: E67P9Y3Q | B37: Acquisition | C37: Rosalina Dieter | D37: =_xlfn.XLOOKUP(C37,sales_teams!A:A,sales_teams!B:B,"") -> W100826 | E37: =_xlfn.XLOOKUP(C37,sales_teams!A:A,sales_teams!C:C,"") -> Celia Rouche | F37: =_xlfn.XLOOKUP(C37,sales_teams!A:A,sales_teams!D:D,"") -> West | G37: GTX Basic | H37: =_xlfn.XLOOKUP(G37,products!A:A,products!B:B,"") -> GTX | I37: Green-Plus | J37: =_xlfn.XLOOKUP(I37,accounts!A:A,accounts!B:B,"") -> services | K37: =_xlfn.XLOOKUP(I37,accounts!A:A,accounts!F:F,"") -> Mid-Market | L37: Won | M37: Product Superiority | N37: Enigma Analytics | O37: 42686 | P37: 42797 | Q37: =_xlfn.XLOOKUP(G37,products!A:A,products!C:C,"") -> 550 | R37: 13 | S37: =Q37*R37 -> 7150
A38: AT3MMVIS | B38: Diversification | C38: Wilburn Farren | D38: =_xlfn.XLOOKUP(C38,sales_teams!A:A,sales_teams!B:B,"") -> E680402 | E38: =_xlfn.XLOOKUP(C38,sales_teams!A:A,sales_teams!C:C,"") -> Cara Losch | F38: =_xlfn.XLOOKUP(C38,sales_teams!A:A,sales_teams!D:D,"") -> East | G38: MG Advanced | H38: =_xlfn.XLOOKUP(G38,products!A:A,products!B:B,"") -> MG | I38: The New York Inquirer | J38: =_xlfn.XLOOKUP(I38,accounts!A:A,accounts!B:B,"") -> medical | K38: =_xlfn.XLOOKUP(I38,accounts!A:A,accounts!F:F,"") -> SMB | L38: Won | M38: Product Superiority | N38: Enigma Analytics | O38: 42686 | P38: 42801 | Q38: =_xlfn.XLOOKUP(G38,products!A:A,products!C:C,"") -> 3393 | R38: 20 | S38: =Q38*R38 -> 67860
A39: REJ11LRY | B39: Expansion | C39: Garret Kinder | D39: =_xlfn.XLOOKUP(C39,sales_teams!A:A,sales_teams!B:B,"") -> E86134 | E39: =_xlfn.XLOOKUP(C39,sales_teams!A:A,sales_teams!C:C,"") -> Cara Losch | F39: =_xlfn.XLOOKUP(C39,sales_teams!A:A,sales_teams!D:D,"") -> East | G39: GTX Plus Basic | H39: =_xlfn.XLOOKUP(G39,products!A:A,products!B:B,"") -> GTX | I39: Mathtouch | J39: =_xlfn.XLOOKUP(I39,accounts!A:A,accounts!B:B,"") -> marketing | K39: =_xlfn.XLOOKUP(I39,accounts!A:A,accounts!F:F,"") -> Enterprise | L39: Won | M39: Product Superiority | N39: Ivy Green-Tech | O39: 42687 | P39: 42808 | Q39: =_xlfn.XLOOKUP(G39,products!A:A,products!C:C,"") -> 1096 | R39: 23 | S39: =Q39*R39 -> 25208
... A43: CZVN09WN | B43: Retention | C43: Darcel Schlecht | D43: =_xlfn.XLOOKUP(C43,sales_teams!A:A,sales_teams!B:B,"") -> C486814 | E43: =_xlfn.XLOOKUP(C43,sales_teams!A:A,sales_teams!C:C,"") -> Melvin Marxen | F43: =_xlfn.XLOOKUP(C43,sales_teams!A:A,sales_teams!D:D,"") -> Central | G43: GTX Plus Basic | H43: =_xlfn.XLOOKUP(G43,products!A:A,products!B:B,"") -> GTX | I43: Konmatfix | J43: =_xlfn.XLOOKUP(I43,accounts!A:A,accounts!B:B,"") -> marketing | K43: =_xlfn.XLOOKUP(I43,accounts!A:A,accounts!F:F,"") -> Mid-Market | L43: Won | M43: Executive Relationship | N43: Cobblepot Exports | O43: 42688 | P43: 42814 | Q43: =_xlfn.XLOOKUP(G43,products!A:A,products!C:C,"") -> 1096 | R43: 40 | S43: =Q43*R43 -> 43840
A44: EG7OFLFR | B44: Expansion | C44: Kami Bicknell | D44: =_xlfn.XLOOKUP(C44,sales_teams!A:A,sales_teams!B:B,"") -> W596440 | E44: =_xlfn.XLOOKUP(C44,sales_teams!A:A,sales_teams!C:C,"") -> Summer Sewald | F44: =_xlfn.XLOOKUP(C44,sales_teams!A:A,sales_teams!D:D,"") -> West | G44: GTX Basic | H44: =_xlfn.XLOOKUP(G44,products!A:A,products!B:B,"") -> GTX | J44: =_xlfn.XLOOKUP(I44,accounts!A:A,accounts!B:B,"") -> 0 | K44: =_xlfn.XLOOKUP(I44,accounts!A:A,accounts!F:F,"") -> 0 | L44: Engaging | N44: TBD | O44: 42688 | Q44: =_xlfn.XLOOKUP(G44,products!A:A,products!C:C,"") -> 550 | R44: 12 | S44: =Q44*R44 -> 6600
A45: 30UQWUKB | B45: Expansion | C45: Marty Freudenburg | D45: =_xlfn.XLOOKUP(C45,sales_teams!A:A,sales_teams!B:B,"") -> C234392 | E45: =_xlfn.XLOOKUP(C45,sales_teams!A:A,sales_teams!C:C,"") -> Melvin Marxen | F45: =_xlfn.XLOOKUP(C45,sales_teams!A:A,sales_teams!D:D,"") -> Central | G45: GTX Plus Basic | H45: =_xlfn.XLOOKUP(G45,products!A:A,products!B:B,"") -> GTX | I45: Genco Pura Olive Oil Company | J45: =_xlfn.XLOOKUP(I45,accounts!A:A,accounts!B:B,"") -> retail | K45: =_xlfn.XLOOKUP(I45,accounts!A:A,accounts!F:F,"") -> Mid-Market | L45: Won | M45: Advanced Technology | N45: Ivy Green-Tech | O45: 42689 | P45: 42814 | Q45: =_xlfn.XLOOKUP(G45,products!A:A,products!C:C,"") -> 1096 | R45: 26 | S45: =Q45*R45 -> 28496
A46: OLVI7L8M | B46: Retention | C46: Cassey Cress | D46: =_xlfn.XLOOKUP(C46,sales_teams!A:A,sales_teams!B:B,"") -> E619716 | E46: =_xlfn.XLOOKUP(C46,sales_teams!A:A,sales_teams!C:C,"") -> Rocco Neubert | F46: =_xlfn.XLOOKUP(C46,sales_teams!A:A,sales_teams!D:D,"") -> East | G46: GTX Pro | H46: =_xlfn.XLOOKUP(G46,products!A:A,products!B:B,"") -> GTX | J46: =_xlfn.XLOOKUP(I46,accounts!A:A,accounts!B:B,"") -> 0 | K46: =_xlfn.XLOOKUP(I46,accounts!A:A,accounts!F:F,"") -> 0 | L46: Engaging | N46: TBD | O46: 42690 | Q46: =_xlfn.XLOOKUP(G46,products!A:A,products!C:C,"") -> 4821 | R46: 49 | S46: =Q46*R46 -> 236229
A47: 97UN20YY | B47: Retention | C47: Darcel Schlecht | D47: =_xlfn.XLOOKUP(C47,sales_teams!A:A,sales_teams!B:B,"") -> C486814 | E47: =_xlfn.XLOOKUP(C47,sales_teams!A:A,sales_teams!C:C,"") -> Melvin Marxen | F47: =_xlfn.XLOOKUP(C47,sales_teams!A:A,sales_teams!D:D,"") -> Central | G47: MG Advanced | H47: =_xlfn.XLOOKUP(G47,products!A:A,products!B:B,"") -> MG | I47: Conecom | J47: =_xlfn.XLOOKUP(I47,accounts!A:A,accounts!B:B,"") -> technolgy | K47: =_xlfn.XLOOKUP(I47,accounts!A:A,accounts!F:F,"") -> Mid-Market | L47: Won | M47: Executive Relationship | N47: Falconia Enterprises | O47: 42690 | P47: 42808 | Q47: =_xlfn.XLOOKUP(G47,products!A:A,products!C:C,"") -> 3393 | R47: 12 | S47: =Q47*R47 -> 40716
A48: JXLERZ9O | B48: Acquisition | C48: Kary Hendrixson | D48: =_xlfn.XLOOKUP(C48,sales_teams!A:A,sales_teams!B:B,"") -> W674591 | E48: =_xlfn.XLOOKUP(C48,sales_teams!A:A,sales_teams!C:C,"") -> Summer Sewald | F48: =_xlfn.XLOOKUP(C48,sales_teams!A:A,sales_teams!D:D,"") -> West | G48: GTX Basic | H48: =_xlfn.XLOOKUP(G48,products!A:A,products!B:B,"") -> GTX | I48: Golddex | J48: =_xlfn.XLOOKUP(I48,accounts!A:A,accounts!B:B,"") -> finance | K48: =_xlfn.XLOOKUP(I48,accounts!A:A,accounts!F:F,"") -> SMB | L48: Won | M48: Strategic Timing | N48: Cobblepot Exports | O48: 42690 | P48: 42825 | Q48: =_xlfn.XLOOKUP(G48,products!A:A,products!C:C,"") -> 550 | R48: 25 | S48: =Q48*R48 -> 13750
A49: 6ROE69W5 | B49: Retention | C49: Rosalina Dieter | D49: =_xlfn.XLOOKUP(C49,sales_teams!A:A,sales_teams!B:B,"") -> W100826 | E49: =_xlfn.XLOOKUP(C49,sales_teams!A:A,sales_teams!C:C,"") -> Celia Rouche | F49: =_xlfn.XLOOKUP(C49,sales_teams!A:A,sales_teams!D:D,"") -> West | G49: GTX Basic | H49: =_xlfn.XLOOKUP(G49,products!A:A,products!B:B,"") -> GTX | I49: Plexzap | J49: =_xlfn.XLOOKUP(I49,accounts!A:A,accounts!B:B,"") -> retail | K49: =_xlfn.XLOOKUP(I49,accounts!A:A,accounts!F:F,"") -> Mid-Market | L49: Lost | M49: Competitor Selection | N49: Cobblepot Exports | O49: 42690 | P49: 42805 | Q49: =_xlfn.XLOOKUP(G49,products!A:A,products!C:C,"") -> 550 | R49: 22 | S49: =Q49*R49 -> 12100
A50: 0DFXFKT7 | B50: Retention | C50: Darcel Schlecht | D50: =_xlfn.XLOOKUP(C50,sales_teams!A:A,sales_teams!B:B,"") -> C486814 | E50: =_xlfn.XLOOKUP(C50,sales_teams!A:A,sales_teams!C:C,"") -> Melvin Marxen | F50: =_xlfn.XLOOKUP(C50,sales_teams!A:A,sales_teams!D:D,"") -> Central | G50: GTX Plus Basic | H50: =_xlfn.XLOOKUP(G50,products!A:A,products!B:B,"") -> GTX | I50: Rundofase | J50: =_xlfn.XLOOKUP(I50,accounts!A:A,accounts!B:B,"") -> technolgy | K50: =_xlfn.XLOOKUP(I50,accounts!A:A,accounts!F:F,"") -> Mid-Market | L50: Lost | M50: Strategic Pivot | N50: Enigma Analytics | O50: 42691 | P50: 42815 | Q50: =_xlfn.XLOOKUP(G50,products!A:A,products!C:C,"") -> 1096 | R50: 43 | S50: =Q50*R50 -> 47128
A51: XKMZVSN4 | B51: Expansion | C51: James Ascencio | D51: =_xlfn.XLOOKUP(C51,sales_teams!A:A,sales_teams!B:B,"") -> W249222 | E51: =_xlfn.XLOOKUP(C51,sales_teams!A:A,sales_teams!C:C,"") -> Summer Sewald | F51: =_xlfn.XLOOKUP(C51,sales_teams!A:A,sales_teams!D:D,"") -> West | G51: GTX Plus Pro | H51: =_xlfn.XLOOKUP(G51,products!A:A,products!B:B,"") -> GTX | I51: Sonron | J51: =_xlfn.XLOOKUP(I51,accounts!A:A,accounts!B:B,"") -> telecommunications | K51: =_xlfn.XLOOKUP(I51,accounts!A:A,accounts!F:F,"") -> Enterprise | L51: Won | M51: Executive Relationship | N51: Cobblepot Exports | O51: 42691 | P51: 42799 | Q51: =_xlfn.XLOOKUP(G51,products!A:A,products!C:C,"") -> 5482 | R51: 40 | S51: =Q51*R51 -> 219280
A52: IU8V0BZK | B52: Expansion | C52: Marty Freudenburg | D52: =_xlfn.XLOOKUP(C52,sales_teams!A:A,sales_teams!B:B,"") -> C234392 | E52: =_xlfn.XLOOKUP(C52,sales_teams!A:A,sales_teams!C:C,"") -> Melvin Marxen | F52: =_xlfn.XLOOKUP(C52,sales_teams!A:A,sales_teams!D:D,"") -> Central | G52: GTX Plus Basic | H52: =_xlfn.XLOOKUP(G52,products!A:A,products!B:B,"") -> GTX | I52: Finhigh | J52: =_xlfn.XLOOKUP(I52,accounts!A:A,accounts!B:B,"") -> finance | K52: =_xlfn.XLOOKUP(I52,accounts!A:A,accounts!F:F,"") -> Mid-Market | L52: Won | M52: Brand Uniqueness | N52: Ivy Green-Tech | O52: 42691 | P52: 42811 | Q52: =_xlfn.XLOOKUP(G52,products!A:A,products!C:C,"") -> 1096 | R52: 29 | S52: =Q52*R52 -> 31784
A53: XY42936P | B53: Retention | C53: Maureen Marcano | D53: =_xlfn.XLOOKUP(C53,sales_teams!A:A,sales_teams!B:B,"") -> W960943 | E53: =_xlfn.XLOOKUP(C53,sales_teams!A:A,sales_teams!C:C,"") -> Summer Sewald | F53: =_xlfn.XLOOKUP(C53,sales_teams!A:A,sales_teams!D:D,"") -> West | G53: GTX Plus Basic | H53: =_xlfn.XLOOKUP(G53,products!A:A,products!B:B,"") -> GTX | I53: Finjob | J53: =_xlfn.XLOOKUP(I53,accounts!A:A,accounts!B:B,"") -> employment | K53: =_xlfn.XLOOKUP(I53,accounts!A:A,accounts!F:F,"") -> Mid-Market | L53: Won | M53: Advanced Technology | N53: Falconia Enterprises | O53: 42691 | P53: 42807 | Q53: =_xlfn.XLOOKUP(G53,products!A:A,products!C:C,"") -> 1096 | R53: 7 | S53: =Q53*R53 -> 7672
A54: XRN54MBM | B54: Expansion | C54: Niesha Huffines | D54: =_xlfn.XLOOKUP(C54,sales_teams!A:A,sales_teams!B:B,"") -> C961860 | E54: =_xlfn.XLOOKUP(C54,sales_teams!A:A,sales_teams!C:C,"") -> Melvin Marxen | F54: =_xlfn.XLOOKUP(C54,sales_teams!A:A,sales_teams!D:D,"") -> Central | G54: GTX Basic | H54: =_xlfn.XLOOKUP(G54,products!A:A,products!B:B,"") -> GTX | I54: Ron-tech | J54: =_xlfn.XLOOKUP(I54,accounts!A:A,accounts!B:B,"") -> medical | K54: =_xlfn.XLOOKUP(I54,accounts!A:A,accounts!F:F,"") -> Enterprise | L54: Won | M54: Product Superiority | N54: Enigma Analytics | O54: 42691 | P54: 42799 | Q54: =_xlfn.XLOOKUP(G54,products!A:A,products!C:C,"") -> 550 | R54: 30 | S54: =Q54*R54 -> 16500
A55: 2V848WZD | B55: Expansion | C55: Lajuana Vencill | D55: =_xlfn.XLOOKUP(C55,sales_teams!A:A,sales_teams!B:B,"") -> C100201 | E55: =_xlfn.XLOOKUP(C55,sales_teams!A:A,sales_teams!C:C,"") -> Dustin Brinkmann | F55: =_xlfn.XLOOKUP(C55,sales_teams!A:A,sales_teams!D:D,"") -> Central | G55: MG Advanced | H55: =_xlfn.XLOOKUP(G55,products!A:A,products!B:B,"") -> MG | I55: Stanredtax | J55: =_xlfn.XLOOKUP(I55,accounts!A:A,accounts!B:B,"") -> finance | K55: =_xlfn.XLOOKUP(I55,accounts!A:A,accounts!F:F,"") -> Mid-Market | L55: Won | M55: Executive Relationship | N55: Falconia Enterprises | O55: 42692 | P55: 42798 | Q55: =_xlfn.XLOOKUP(G55,products!A:A,products!C:C,"") -> 3393 | R55: 40 | S55: =Q55*R55 -> 135720
A56: ONYNTUCG | B56: Retention | C56: Darcel Schlecht | D56: =_xlfn.XLOOKUP(C56,sales_teams!A:A,sales_teams!B:B,"") -> C486814 | E56: =_xlfn.XLOOKUP(C56,sales_teams!A:A,sales_teams!C:C,"") -> Melvin Marxen | F56: =_xlfn.XLOOKUP(C56,sales_teams!A:A,sales_teams!D:D,"") -> Central | G56: GTX Pro | H56: =_xlfn.XLOOKUP(G56,products!A:A,products!B:B,"") -> GTX | I56: Funholding | J56: =_xlfn.XLOOKUP(I56,accounts!A:A,accounts!B:B,"") -> finance | K56: =_xlfn.XLOOKUP(I56,accounts!A:A,accounts!F:F,"") -> Enterprise | L56: Lost | M56: Feature Requirements | N56: Cobblepot Exports | O56: 42693 | P56: 42811 | Q56: =_xlfn.XLOOKUP(G56,products!A:A,products!C:C,"") -> 4821 | R56: 39 | S56: =Q56*R56 -> 188019
A57: HIOHX80Y | B57: Diversification | C57: Darcel Schlecht | D57: =_xlfn.XLOOKUP(C57,sales_teams!A:A,sales_teams!B:B,"") -> C486814 | E57: =_xlfn.XLOOKUP(C57,sales_teams!A:A,sales_teams!C:C,"") -> Melvin Marxen | F57: =_xlfn.XLOOKUP(C57,sales_teams!A:A,sales_teams!D:D,"") -> Central | G57: MG Advanced | H57: =_xlfn.XLOOKUP(G57,products!A:A,products!B:B,"") -> MG | I57: Gogozoom | J57: =_xlfn.XLOOKUP(I57,accounts!A:A,accounts!B:B,"") -> telecommunications | K57: =_xlfn.XLOOKUP(I57,accounts!A:A,accounts!F:F,"") -> SMB | L57: Won | M57: Advanced Technology | N57: Ivy Green-Tech | O57: 42693 | P57: 42812 | Q57: =_xlfn.XLOOKUP(G57,products!A:A,products!C:C,"") -> 3393 | R57: 10 | S57: =Q57*R57 -> 33930
A58: F5U1ACDD | B58: Expansion | C58: Kami Bicknell | D58: =_xlfn.XLOOKUP(C58,sales_teams!A:A,sales_teams!B:B,"") -> W596440 | E58: =_xlfn.XLOOKUP(C58,sales_teams!A:A,sales_teams!C:C,"") -> Summer Sewald | F58: =_xlfn.XLOOKUP(C58,sales_teams!A:A,sales_teams!D:D,"") -> West | G58: GTX Plus Basic | H58: =_xlfn.XLOOKUP(G58,products!A:A,products!B:B,"") -> GTX | J58: =_xlfn.XLOOKUP(I58,accounts!A:A,accounts!B:B,"") -> 0 | K58: =_xlfn.XLOOKUP(I58,accounts!A:A,accounts!F:F,"") -> 0 | L58: Engaging | N58: TBD | O58: 42693 | Q58: =_xlfn.XLOOKUP(G58,products!A:A,products!C:C,"") -> 1096 | R58: 18 | S58: =Q58*R58 -> 19728
A59: LPKT07PV | B59: Retention | C59: Boris Faz | D59: =_xlfn.XLOOKUP(C59,sales_teams!A:A,sales_teams!B:B,"") -> E558564 | E59: =_xlfn.XLOOKUP(C59,sales_teams!A:A,sales_teams!C:C,"") -> Rocco Neubert | F59: =_xlfn.XLOOKUP(C59,sales_teams!A:A,sales_teams!D:D,"") -> East | G59: GTX Pro | H59: =_xlfn.XLOOKUP(G59,products!A:A,products!B:B,"") -> GTX | I59: Opentech | J59: =_xlfn.XLOOKUP(I59,accounts!A:A,accounts!B:B,"") -> finance | K59: =_xlfn.XLOOKUP(I59,accounts!A:A,accounts!F:F,"") -> SMB | L59: Won | M59: Brand Uniqueness | N59: Enigma Analytics | O59: 42694 | P59: 42817 | Q59: =_xlfn.XLOOKUP(G59,products!A:A,products!C:C,"") -> 4821 | R59: 29 | S59: =Q59*R59 -> 139809
A60: WPB2SLIG | B60: Expansion | C60: Donn Cantrell | D60: =_xlfn.XLOOKUP(C60,sales_teams!A:A,sales_teams!B:B,"") -> E262141 | E60: =_xlfn.XLOOKUP(C60,sales_teams!A:A,sales_teams!C:C,"") -> Rocco Neubert | F60: =_xlfn.XLOOKUP(C60,sales_teams!A:A,sales_teams!D:D,"") -> East | G60: GTX Plus Pro | H60: =_xlfn.XLOOKUP(G60,products!A:A,products!B:B,"") -> GTX | I60: Silis | J60: =_xlfn.XLOOKUP(I60,accounts!A:A,accounts!B:B,"") -> medical | K60: =_xlfn.XLOOKUP(I60,accounts!A:A,accounts!F:F,"") -> Enterprise | L60: Won | M60: Brand Uniqueness | N60: Falconia Enterprises | O60: 42694 | P60: 42808 | Q60: =_xlfn.XLOOKUP(G60,products!A:A,products!C:C,"") -> 5482 | R60: 27 | S60: =Q60*R60 -> 148014
A61: XUSUEAV7 | B61: Expansion | C61: Elease Gluck | D61: =_xlfn.XLOOKUP(C61,sales_teams!A:A,sales_teams!B:B,"") -> W172727 | E61: =_xlfn.XLOOKUP(C61,sales_teams!A:A,sales_teams!C:C,"") -> Celia Rouche | F61: =_xlfn.XLOOKUP(C61,sales_teams!A:A,sales_teams!D:D,"") -> West | G61: GTK 500 | H61: =_xlfn.XLOOKUP(G61,products!A:A,products!B:B,"") -> GTK | I61: Zoomit | J61: =_xlfn.XLOOKUP(I61,accounts!A:A,accounts!B:B,"") -> entertainment | K61: =_xlfn.XLOOKUP(I61,accounts!A:A,accounts!F:F,"") -> SMB | L61: Won | M61: Product Superiority | N61: Ivy Green-Tech | O61: 42694 | P61: 42803 | Q61: =_xlfn.XLOOKUP(G61,products!A:A,products!C:C,"") -> 26768 | R61: 14 | S61: =Q61*R61 -> 374752
A62: ZZY4516R | B62: Expansion | C62: Hayden Neloms | D62: =_xlfn.XLOOKUP(C62,sales_teams!A:A,sales_teams!B:B,"") -> W815792 | E62: =_xlfn.XLOOKUP(C62,sales_teams!A:A,sales_teams!C:C,"") -> Celia Rouche | F62: =_xlfn.XLOOKUP(C62,sales_teams!A:A,sales_teams!D:D,"") -> West | G62: MG Advanced | H62: =_xlfn.XLOOKUP(G62,products!A:A,products!B:B,"") -> MG | J62: =_xlfn.XLOOKUP(I62,accounts!A:A,accounts!B:B,"") -> 0 | K62: =_xlfn.XLOOKUP(I62,accounts!A:A,accounts!F:F,"") -> 0 | L62: Engaging | N62: TBD | O62: 42694 | Q62: =_xlfn.XLOOKUP(G62,products!A:A,products!C:C,"") -> 3393 | R62: 43 | S62: =Q62*R62 -> 145899
A63: 3TYPII47 | B63: Diversification | C63: Kami Bicknell | D63: =_xlfn.XLOOKUP(C63,sales_teams!A:A,sales_teams!B:B,"") -> W596440 | E63: =_xlfn.XLOOKUP(C63,sales_teams!A:A,sales_teams!C:C,"") -> Summer Sewald | F63: =_xlfn.XLOOKUP(C63,sales_teams!A:A,sales_teams!D:D,"") -> West | G63: GTX Plus Basic | H63: =_xlfn.XLOOKUP(G63,products!A:A,products!B:B,"") -> GTX | I63: Goodsilron | J63: =_xlfn.XLOOKUP(I63,accounts!A:A,accounts!B:B,"") -> marketing | K63: =_xlfn.XLOOKUP(I63,accounts!A:A,accounts!F:F,"") -> Enterprise | L63: Won | M63: Strategic Timing | N63: Cobblepot Exports | O63: 42694 | P63: 42797 | Q63: =_xlfn.XLOOKUP(G63,products!A:A,products!C:C,"") -> 1096 | R63: 30 | S63: =Q63*R63 -> 32880
A64: 7WAX8Z8O | B64: Expansion | C64: Lajuana Vencill | D64: =_xlfn.XLOOKUP(C64,sales_teams!A:A,sales_teams!B:B,"") -> C100201 | E64: =_xlfn.XLOOKUP(C64,sales_teams!A:A,sales_teams!C:C,"") -> Dustin Brinkmann | F64: =_xlfn.XLOOKUP(C64,sales_teams!A:A,sales_teams!D:D,"") -> Central | G64: MG Advanced | H64: =_xlfn.XLOOKUP(G64,products!A:A,products!B:B,"") -> MG | I64: Cancity | J64: =_xlfn.XLOOKUP(I64,accounts!A:A,accounts!B:B,"") -> retail | K64: =_xlfn.XLOOKUP(I64,accounts!A:A,accounts!F:F,"") -> Mid-Market | L64: Lost | M64: Budget Misalignment | N64: Enigma Analytics | O64: 42694 | P64: 42802 | Q64: =_xlfn.XLOOKUP(G64,products!A:A,products!C:C,"") -> 3393 | R64: 5 | S64: =Q64*R64 -> 16965
A65: MYDUMR3R | B65: Acquisition | C65: Lajuana Vencill | D65: =_xlfn.XLOOKUP(C65,sales_teams!A:A,sales_teams!B:B,"") -> C100201 | E65: =_xlfn.XLOOKUP(C65,sales_teams!A:A,sales_teams!C:C,"") -> Dustin Brinkmann | F65: =_xlfn.XLOOKUP(C65,sales_teams!A:A,sales_teams!D:D,"") -> Central | G65: GTX Basic | H65: =_xlfn.XLOOKUP(G65,products!A:A,products!B:B,"") -> GTX | I65: Rangreen | J65: =_xlfn.XLOOKUP(I65,accounts!A:A,accounts!B:B,"") -> technolgy | K65: =_xlfn.XLOOKUP(I65,accounts!A:A,accounts!F:F,"") -> Enterprise | L65: Won | M65: Executive Relationship | N65: Cobblepot Exports | O65: 42694 | P65: 42798 | Q65: =_xlfn.XLOOKUP(G65,products!A:A,products!C:C,"") -> 550 | R65: 44 | S65: =Q65*R65 -> 24200
A66: 0DRC1U9Q | B66: Expansion | C66: Maureen Marcano | D66: =_xlfn.XLOOKUP(C66,sales_teams!A:A,sales_teams!B:B,"") -> W960943 | E66: =_xlfn.XLOOKUP(C66,sales_teams!A:A,sales_teams!C:C,"") -> Summer Sewald | F66: =_xlfn.XLOOKUP(C66,sales_teams!A:A,sales_teams!D:D,"") -> West | G66: GTX Basic | H66: =_xlfn.XLOOKUP(G66,products!A:A,products!B:B,"") -> GTX | I66: Green-Plus | J66: =_xlfn.XLOOKUP(I66,accounts!A:A,accounts!B:B,"") -> services | K66: =_xlfn.XLOOKUP(I66,accounts!A:A,accounts!F:F,"") -> Mid-Market | L66: Engaging | N66: TBD | O66: 42694 | Q66: =_xlfn.XLOOKUP(G66,products!A:A,products!C:C,"") -> 550 | R66: 45 | S66: =Q66*R66 -> 24750
A67: 37JFKD4I | B67: Expansion | C67: Niesha Huffines | D67: =_xlfn.XLOOKUP(C67,sales_teams!A:A,sales_teams!B:B,"") -> C961860 | E67: =_xlfn.XLOOKUP(C67,sales_teams!A:A,sales_teams!C:C,"") -> Melvin Marxen | F67: =_xlfn.XLOOKUP(C67,sales_teams!A:A,sales_teams!D:D,"") -> Central | G67: GTX Plus Basic | H67: =_xlfn.XLOOKUP(G67,products!A:A,products!B:B,"") -> GTX | I67: dambase | J67: =_xlfn.XLOOKUP(I67,accounts!A:A,accounts!B:B,"") -> marketing | K67: =_xlfn.XLOOKUP(I67,accounts!A:A,accounts!F:F,"") -> Mid-Market | L67: Won | M67: Product Superiority | N67: Falconia Enterprises | O67: 42694 | P67: 42803 | Q67: =_xlfn.XLOOKUP(G67,products!A:A,products!C:C,"") -> 1096 | R67: 24 | S67: =Q67*R67 -> 26304
A68: 25YKPHX8 | B68: Acquisition | C68: Donn Cantrell | D68: =_xlfn.XLOOKUP(C68,sales_teams!A:A,sales_teams!B:B,"") -> E262141 | E68: =_xlfn.XLOOKUP(C68,sales_teams!A:A,sales_teams!C:C,"") -> Rocco Neubert | F68: =_xlfn.XLOOKUP(C68,sales_teams!A:A,sales_teams!D:D,"") -> East | G68: GTX Basic | H68: =_xlfn.XLOOKUP(G68,products!A:A,products!B:B,"") -> GTX | I68: Kan-code | J68: =_xlfn.XLOOKUP(I68,accounts!A:A,accounts!B:B,"") -> software | K68: =_xlfn.XLOOKUP(I68,accounts!A:A,accounts!F:F,"") -> Enterprise | L68: Won | M68: Executive Relationship | N68: Enigma Analytics | O68: 42695 | P68: 42815 | Q68: =_xlfn.XLOOKUP(G68,products!A:A,products!C:C,"") -> 550 | R68: 22 | S68: =Q68*R68 -> 12100
A69: BXXMA7F3 | B69: Diversification | C69: Hayden Neloms | D69: =_xlfn.XLOOKUP(C69,sales_teams!A:A,sales_teams!B:B,"") -> W815792 | E69: =_xlfn.XLOOKUP(C69,sales_teams!A:A,sales_teams!C:C,"") -> Celia Rouche | F69: =_xlfn.XLOOKUP(C69,sales_teams!A:A,sales_teams!D:D,"") -> West | G69: MG Advanced | H69: =_xlfn.XLOOKUP(G69,products!A:A,products!B:B,"") -> MG | I69: Nam-zim | J69: =_xlfn.XLOOKUP(I69,accounts!A:A,accounts!B:B,"") -> services | K69: =_xlfn.XLOOKUP(I69,accounts!A:A,accounts!F:F,"") -> Mid-Market | L69: Lost | M69: Budget Misalignment | N69: Ivy Green-Tech | O69: 42695 | P69: 42795 | Q69: =_xlfn.XLOOKUP(G69,products!A:A,products!C:C,"") -> 3393 | R69: 5 | S69: =Q69*R69 -> 16965
A70: GIUUTBXM | B70: Retention | C70: Kary Hendrixson | D70: =_xlfn.XLOOKUP(C70,sales_teams!A:A,sales_teams!B:B,"") -> W674591 | E70: =_xlfn.XLOOKUP(C70,sales_teams!A:A,sales_teams!C:C,"") -> Summer Sewald | F70: =_xlfn.XLOOKUP(C70,sales_teams!A:A,sales_teams!D:D,"") -> West | G70: GTX Pro | H70: =_xlfn.XLOOKUP(G70,products!A:A,products!B:B,"") -> GTX | I70: Y-corporation | J70: =_xlfn.XLOOKUP(I70,accounts!A:A,accounts!B:B,"") -> employment | K70: =_xlfn.XLOOKUP(I70,accounts!A:A,accounts!F:F,"") -> Enterprise | L70: Won | M70: Product Superiority | N70: Enigma Analytics | O70: 42695 | P70: 42808 | Q70: =_xlfn.XLOOKUP(G70,products!A:A,products!C:C,"") -> 4821 | R70: 43 | S70: =Q70*R70 -> 207303
A71: MFX2LR1Q | B71: Retention | C71: Lajuana Vencill | D71: =_xlfn.XLOOKUP(C71,sales_teams!A:A,sales_teams!B:B,"") -> C100201 | E71: =_xlfn.XLOOKUP(C71,sales_teams!A:A,sales_teams!C:C,"") -> Dustin Brinkmann | F71: =_xlfn.XLOOKUP(C71,sales_teams!A:A,sales_teams!D:D,"") -> Central | G71: MG Advanced | H71: =_xlfn.XLOOKUP(G71,products!A:A,products!B:B,"") -> MG | I71: Ron-tech | J71: =_xlfn.XLOOKUP(I71,accounts!A:A,accounts!B:B,"") -> medical | K71: =_xlfn.XLOOKUP(I71,accounts!A:A,accounts!F:F,"") -> Enterprise | L71: Won | M71: Product Superiority | N71: Ivy Green-Tech | O71: 42695 | P71: 42809 | Q71: =_xlfn.XLOOKUP(G71,products!A:A,products!C:C,"") -> 3393 | R71: 45 | S71: =Q71*R71 -> 152685
A72: DUHE9FLY | B72: Expansion | C72: Marty Freudenburg | D72: =_xlfn.XLOOKUP(C72,sales_teams!A:A,sales_teams!B:B,"") -> C234392 | E72: =_xlfn.XLOOKUP(C72,sales_teams!A:A,sales_teams!C:C,"") -> Melvin Marxen | F72: =_xlfn.XLOOKUP(C72,sales_teams!A:A,sales_teams!D:D,"") -> Central | G72: GTX Pro | H72: =_xlfn.XLOOKUP(G72,products!A:A,products!B:B,"") -> GTX | I72: Conecom | J72: =_xlfn.XLOOKUP(I72,accounts!A:A,accounts!B:B,"") -> technolgy | K72: =_xlfn.XLOOKUP(I72,accounts!A:A,accounts!F:F,"") -> Mid-Market | L72: Won | M72: Advanced Technology | N72: Cobblepot Exports | O72: 42695 | P72: 42795 | Q72: =_xlfn.XLOOKUP(G72,products!A:A,products!C:C,"") -> 4821 | R72: 14 | S72: =Q72*R72 -> 67494
A73: 96BSG7R1 | B73: Retention | C73: Zane Levy | D73: =_xlfn.XLOOKUP(C73,sales_teams!A:A,sales_teams!B:B,"") -> W202814 | E73: =_xlfn.XLOOKUP(C73,sales_teams!A:A,sales_teams!C:C,"") -> Summer Sewald | F73: =_xlfn.XLOOKUP(C73,sales_teams!A:A,sales_teams!D:D,"") -> West | G73: GTX Plus Basic | H73: =_xlfn.XLOOKUP(G73,products!A:A,products!B:B,"") -> GTX | I73: Sunnamplex | J73: =_xlfn.XLOOKUP(I73,accounts!A:A,accounts!B:B,"") -> marketing | K73: =_xlfn.XLOOKUP(I73,accounts!A:A,accounts!F:F,"") -> Mid-Market | L73: Lost | M73: Competitor Selection | N73: Enigma Analytics | O73: 42695 | P73: 42811 | Q73: =_xlfn.XLOOKUP(G73,products!A:A,products!C:C,"") -> 1096 | R73: 18 | S73: =Q73*R73 -> 19728
A74: 7FQMSWIX | B74: Expansion | C74: Corliss Cosme | D74: =_xlfn.XLOOKUP(C74,sales_teams!A:A,sales_teams!B:B,"") -> E500449 | E74: =_xlfn.XLOOKUP(C74,sales_teams!A:A,sales_teams!C:C,"") -> Cara Losch | F74: =_xlfn.XLOOKUP(C74,sales_teams!A:A,sales_teams!D:D,"") -> East | G74: MG Special | H74: =_xlfn.XLOOKUP(G74,products!A:A,products!B:B,"") -> MG | I74: Bioplex | J74: =_xlfn.XLOOKUP(I74,accounts!A:A,accounts!B:B,"") -> medical | K74: =_xlfn.XLOOKUP(I74,accounts!A:A,accounts!F:F,"") -> Mid-Market | L74: Won | M74: Product Superiority | N74: Enigma Analytics | O74: 42696 | P74: 42798 | Q74: =_xlfn.XLOOKUP(G74,products!A:A,products!C:C,"") -> 55 | R74: 41 | S74: =Q74*R74 -> 2255
A75: C20AVXN7 | B75: Expansion | C75: Darcel Schlecht | D75: =_xlfn.XLOOKUP(C75,sales_teams!A:A,sales_teams!B:B,"") -> C486814 | E75: =_xlfn.XLOOKUP(C75,sales_teams!A:A,sales_teams!C:C,"") -> Melvin Marxen | F75: =_xlfn.XLOOKUP(C75,sales_teams!A:A,sales_teams!D:D,"") -> Central | G75: GTX Pro | H75: =_xlfn.XLOOKUP(G75,products!A:A,products!B:B,"") -> GTX | I75: Gogozoom | J75: =_xlfn.XLOOKUP(I75,accounts!A:A,accounts!B:B,"") -> telecommunications | K75: =_xlfn.XLOOKUP(I75,accounts!A:A,accounts!F:F,"") -> SMB | L75: Won | M75: Executive Relationship | N75: Enigma Analytics | O75: 42696 | P75: 42808 | Q75: =_xlfn.XLOOKUP(G75,products!A:A,products!C:C,"") -> 4821 | R75: 44 | S75: =Q75*R75 -> 212124
A76: GS1QVWCR | B76: Retention | C76: Kami Bicknell | D76: =_xlfn.XLOOKUP(C76,sales_teams!A:A,sales_teams!B:B,"") -> W596440 | E76: =_xlfn.XLOOKUP(C76,sales_teams!A:A,sales_teams!C:C,"") -> Summer Sewald | F76: =_xlfn.XLOOKUP(C76,sales_teams!A:A,sales_teams!D:D,"") -> West | G76: GTX Basic | H76: =_xlfn.XLOOKUP(G76,products!A:A,products!B:B,"") -> GTX | I76: Plusstrip | J76: =_xlfn.XLOOKUP(I76,accounts!A:A,accounts!B:B,"") -> entertainment | K76: =_xlfn.XLOOKUP(I76,accounts!A:A,accounts!F:F,"") -> SMB | L76: Won | M76: Executive Relationship | N76: Enigma Analytics | O76: 42696 | P76: 42825 | Q76: =_xlfn.XLOOKUP(G76,products!A:A,products!C:C,"") -> 550 | R76: 34 | S76: =Q76*R76 -> 18700
A77: ZWH8FXY3 | B77: Expansion | C77: Marty Freudenburg | D77: =_xlfn.XLOOKUP(C77,sales_teams!A:A,sales_teams!B:B,"") -> C234392 | E77: =_xlfn.XLOOKUP(C77,sales_teams!A:A,sales_teams!C:C,"") -> Melvin Marxen | F77: =_xlfn.XLOOKUP(C77,sales_teams!A:A,sales_teams!D:D,"") -> Central | G77: GTX Basic | H77: =_xlfn.XLOOKUP(G77,products!A:A,products!B:B,"") -> GTX | I77: Toughzap | J77: =_xlfn.XLOOKUP(I77,accounts!A:A,accounts!B:B,"") -> retail | K77: =_xlfn.XLOOKUP(I77,accounts!A:A,accounts!F:F,"") -> SMB | L77: Won | M77: Brand Uniqueness | N77: Enigma Analytics | O77: 42696 | P77: 42797 | Q77: =_xlfn.XLOOKUP(G77,products!A:A,products!C:C,"") -> 550 | R77: 36 | S77: =Q77*R77 -> 19800
A78: 2U94Y3Q9 | B78: Acquisition | C78: Rosie Papadopoulos | D78: =_xlfn.XLOOKUP(C78,sales_teams!A:A,sales_teams!B:B,"") -> E777204 | E78: =_xlfn.XLOOKUP(C78,sales_teams!A:A,sales_teams!C:C,"") -> Cara Losch | F78: =_xlfn.XLOOKUP(C78,sales_teams!A:A,sales_teams!D:D,"") -> East | G78: MG Advanced | H78: =_xlfn.XLOOKUP(G78,products!A:A,products!B:B,"") -> MG | I78: Vehement Capital Partners | J78: =_xlfn.XLOOKUP(I78,accounts!A:A,accounts!B:B,"") -> finance | K78: =_xlfn.XLOOKUP(I78,accounts!A:A,accounts!F:F,"") -> SMB | L78: Lost | M78: Budget Misalignment | N78: Falconia Enterprises | O78: 42696 | P78: 42814 | Q78: =_xlfn.XLOOKUP(G78,products!A:A,products!C:C,"") -> 3393 | R78: 39 | S78: =Q78*R78 -> 132327
... A80: B6B0PNR2 | B80: Retention | C80: Vicki Laflamme | D80: =_xlfn.XLOOKUP(C80,sales_teams!A:A,sales_teams!B:B,"") -> W975078 | E80: =_xlfn.XLOOKUP(C80,sales_teams!A:A,sales_teams!C:C,"") -> Celia Rouche | F80: =_xlfn.XLOOKUP(C80,sales_teams!A:A,sales_teams!D:D,"") -> West | G80: GTX Pro | H80: =_xlfn.XLOOKUP(G80,products!A:A,products!B:B,"") -> GTX | I80: Dalttechnology | J80: =_xlfn.XLOOKUP(I80,accounts!A:A,accounts!B:B,"") -> software | K80: =_xlfn.XLOOKUP(I80,accounts!A:A,accounts!F:F,"") -> SMB | L80: Won | M80: Strategic Timing | N80: Cobblepot Exports | O80: 42696 | P80: 42799 | Q80: =_xlfn.XLOOKUP(G80,products!A:A,products!C:C,"") -> 4821 | R80: 40 | S80: =Q80*R80 -> 192840
A81: M7I5O9YU | B81: Expansion | C81: Corliss Cosme | D81: =_xlfn.XLOOKUP(C81,sales_teams!A:A,sales_teams!B:B,"") -> E500449 | E81: =_xlfn.XLOOKUP(C81,sales_teams!A:A,sales_teams!C:C,"") -> Cara Losch | F81: =_xlfn.XLOOKUP(C81,sales_teams!A:A,sales_teams!D:D,"") -> East | G81: GTX Basic | H81: =_xlfn.XLOOKUP(G81,products!A:A,products!B:B,"") -> GTX | I81: Cheers | J81: =_xlfn.XLOOKUP(I81,accounts!A:A,accounts!B:B,"") -> entertainment | K81: =_xlfn.XLOOKUP(I81,accounts!A:A,accounts!F:F,"") -> Enterprise | L81: Engaging | N81: TBD | O81: 42697 | Q81: =_xlfn.XLOOKUP(G81,products!A:A,products!C:C,"") -> 550 | R81: 14 | S81: =Q81*R81 -> 7700
A82: LXZA2OSZ | B82: Expansion | C82: Corliss Cosme | D82: =_xlfn.XLOOKUP(C82,sales_teams!A:A,sales_teams!B:B,"") -> E500449 | E82: =_xlfn.XLOOKUP(C82,sales_teams!A:A,sales_teams!C:C,"") -> Cara Losch | F82: =_xlfn.XLOOKUP(C82,sales_teams!A:A,sales_teams!D:D,"") -> East | G82: GTX Plus Pro | H82: =_xlfn.XLOOKUP(G82,products!A:A,products!B:B,"") -> GTX | I82: Ontomedia | J82: =_xlfn.XLOOKUP(I82,accounts!A:A,accounts!B:B,"") -> employment | K82: =_xlfn.XLOOKUP(I82,accounts!A:A,accounts!F:F,"") -> Mid-Market | L82: Won | M82: Product Superiority | N82: Enigma Analytics | O82: 42697 | P82: 42797 | Q82: =_xlfn.XLOOKUP(G82,products!A:A,products!C:C,"") -> 5482 | R82: 6 | S82: =Q82*R82 -> 32892
A83: N0ONCYVZ | B83: Retention | C83: Donn Cantrell | D83: =_xlfn.XLOOKUP(C83,sales_teams!A:A,sales_teams!B:B,"") -> E262141 | E83: =_xlfn.XLOOKUP(C83,sales_teams!A:A,sales_teams!C:C,"") -> Rocco Neubert | F83: =_xlfn.XLOOKUP(C83,sales_teams!A:A,sales_teams!D:D,"") -> East | G83: MG Special | H83: =_xlfn.XLOOKUP(G83,products!A:A,products!B:B,"") -> MG | I83: Kinnamplus | J83: =_xlfn.XLOOKUP(I83,accounts!A:A,accounts!B:B,"") -> retail | K83: =_xlfn.XLOOKUP(I83,accounts!A:A,accounts!F:F,"") -> Mid-Market | L83: Lost | M83: Competitor Selection | N83: Ivy Green-Tech | O83: 42697 | P83: 42824 | Q83: =_xlfn.XLOOKUP(G83,products!A:A,products!C:C,"") -> 55 | R83: 41 | S83: =Q83*R83 -> 2255
A84: GYB4W2AU | B84: Diversification | C84: Elease Gluck | D84: =_xlfn.XLOOKUP(C84,sales_teams!A:A,sales_teams!B:B,"") -> W172727 | E84: =_xlfn.XLOOKUP(C84,sales_teams!A:A,sales_teams!C:C,"") -> Celia Rouche | F84: =_xlfn.XLOOKUP(C84,sales_teams!A:A,sales_teams!D:D,"") -> West | G84: MG Advanced | H84: =_xlfn.XLOOKUP(G84,products!A:A,products!B:B,"") -> MG | J84: =_xlfn.XLOOKUP(I84,accounts!A:A,accounts!B:B,"") -> 0 | K84: =_xlfn.XLOOKUP(I84,accounts!A:A,accounts!F:F,"") -> 0 | L84: Engaging | N84: TBD | O84: 42697 | Q84: =_xlfn.XLOOKUP(G84,products!A:A,products!C:C,"") -> 3393 | R84: 4 | S84: =Q84*R84 -> 13572
A85: 513DPFX5 | B85: Expansion | C85: Gladys Colclough | D85: =_xlfn.XLOOKUP(C85,sales_teams!A:A,sales_teams!B:B,"") -> C130664 | E85: =_xlfn.XLOOKUP(C85,sales_teams!A:A,sales_teams!C:C,"") -> Melvin Marxen | F85: =_xlfn.XLOOKUP(C85,sales_teams!A:A,sales_teams!D:D,"") -> Central | G85: GTX Pro | H85: =_xlfn.XLOOKUP(G85,products!A:A,products!B:B,"") -> GTX | I85: Codehow | J85: =_xlfn.XLOOKUP(I85,accounts!A:A,accounts!B:B,"") -> software | K85: =_xlfn.XLOOKUP(I85,accounts!A:A,accounts!F:F,"") -> Mid-Market | L85: Won | M85: Advanced Technology | N85: Enigma Analytics | O85: 42697 | P85: 42797 | Q85: =_xlfn.XLOOKUP(G85,products!A:A,products!C:C,"") -> 4821 | R85: 10 | S85: =Q85*R85 -> 48210
A86: RU023K5W | B86: Expansion | C86: Gladys Colclough | D86: =_xlfn.XLOOKUP(C86,sales_teams!A:A,sales_teams!B:B,"") -> C130664 | E86: =_xlfn.XLOOKUP(C86,sales_teams!A:A,sales_teams!C:C,"") -> Melvin Marxen | F86: =_xlfn.XLOOKUP(C86,sales_teams!A:A,sales_teams!D:D,"") -> Central | G86: MG Advanced | H86: =_xlfn.XLOOKUP(G86,products!A:A,products!B:B,"") -> MG | I86: Finhigh | J86: =_xlfn.XLOOKUP(I86,accounts!A:A,accounts!B:B,"") -> finance | K86: =_xlfn.XLOOKUP(I86,accounts!A:A,accounts!F:F,"") -> Mid-Market | L86: Won | M86: Product Superiority | N86: Enigma Analytics | O86: 42697 | P86: 42811 | Q86: =_xlfn.XLOOKUP(G86,products!A:A,products!C:C,"") -> 3393 | R86: 7 | S86: =Q86*R86 -> 23751
A87: VDIU10RV | B87: Expansion | C87: Markita Hansen | D87: =_xlfn.XLOOKUP(C87,sales_teams!A:A,sales_teams!B:B,"") -> W337844 | E87: =_xlfn.XLOOKUP(C87,sales_teams!A:A,sales_teams!C:C,"") -> Celia Rouche | F87: =_xlfn.XLOOKUP(C87,sales_teams!A:A,sales_teams!D:D,"") -> West | G87: MG Special | H87: =_xlfn.XLOOKUP(G87,products!A:A,products!B:B,"") -> MG | I87: Lexiqvolax | J87: =_xlfn.XLOOKUP(I87,accounts!A:A,accounts!B:B,"") -> medical | K87: =_xlfn.XLOOKUP(I87,accounts!A:A,accounts!F:F,"") -> Mid-Market | L87: Engaging | N87: TBD | O87: 42697 | Q87: =_xlfn.XLOOKUP(G87,products!A:A,products!C:C,"") -> 55 | R87: 26 | S87: =Q87*R87 -> 1430
A88: BZCBQ514 | B88: Expansion | C88: Markita Hansen | D88: =_xlfn.XLOOKUP(C88,sales_teams!A:A,sales_teams!B:B,"") -> W337844 | E88: =_xlfn.XLOOKUP(C88,sales_teams!A:A,sales_teams!C:C,"") -> Celia Rouche | F88: =_xlfn.XLOOKUP(C88,sales_teams!A:A,sales_teams!D:D,"") -> West | G88: GTX Basic | H88: =_xlfn.XLOOKUP(G88,products!A:A,products!B:B,"") -> GTX | I88: Y-corporation | J88: =_xlfn.XLOOKUP(I88,accounts!A:A,accounts!B:B,"") -> employment | K88: =_xlfn.XLOOKUP(I88,accounts!A:A,accounts!F:F,"") -> Enterprise | L88: Won | M88: Product Superiority | N88: Ivy Green-Tech | O88: 42697 | P88: 42795 | Q88: =_xlfn.XLOOKUP(G88,products!A:A,products!C:C,"") -> 550 | R88: 36 | S88: =Q88*R88 -> 19800
A89: HEE6P0QH | B89: Acquisition | C89: Anna Snelling | D89: =_xlfn.XLOOKUP(C89,sales_teams!A:A,sales_teams!B:B,"") -> C265891 | E89: =_xlfn.XLOOKUP(C89,sales_teams!A:A,sales_teams!C:C,"") -> Dustin Brinkmann | F89: =_xlfn.XLOOKUP(C89,sales_teams!A:A,sales_teams!D:D,"") -> Central | G89: MG Advanced | H89: =_xlfn.XLOOKUP(G89,products!A:A,products!B:B,"") -> MG | I89: Statholdings | J89: =_xlfn.XLOOKUP(I89,accounts!A:A,accounts!B:B,"") -> employment | K89: =_xlfn.XLOOKUP(I89,accounts!A:A,accounts!F:F,"") -> SMB | L89: Won | M89: Advanced Technology | N89: Ivy Green-Tech | O89: 42698 | P89: 42819 | Q89: =_xlfn.XLOOKUP(G89,products!A:A,products!C:C,"") -> 3393 | R89: 24 | S89: =Q89*R89 -> 81432
A90: L8CHRJ2B | B90: Retention | C90: Cassey Cress | D90: =_xlfn.XLOOKUP(C90,sales_teams!A:A,sales_teams!B:B,"") -> E619716 | E90: =_xlfn.XLOOKUP(C90,sales_teams!A:A,sales_teams!C:C,"") -> Rocco Neubert | F90: =_xlfn.XLOOKUP(C90,sales_teams!A:A,sales_teams!D:D,"") -> East | G90: MG Advanced | H90: =_xlfn.XLOOKUP(G90,products!A:A,products!B:B,"") -> MG | I90: Umbrella Corporation | J90: =_xlfn.XLOOKUP(I90,accounts!A:A,accounts!B:B,"") -> finance | K90: =_xlfn.XLOOKUP(I90,accounts!A:A,accounts!F:F,"") -> Enterprise | L90: Won | M90: Advanced Technology | N90: Falconia Enterprises | O90: 42698 | P90: 42795 | Q90: =_xlfn.XLOOKUP(G90,products!A:A,products!C:C,"") -> 3393 | R90: 10 | S90: =Q90*R90 -> 33930
A91: 579LZ3F9 | B91: Diversification | C91: Daniell Hammack | D91: =_xlfn.XLOOKUP(C91,sales_teams!A:A,sales_teams!B:B,"") -> E372575 | E91: =_xlfn.XLOOKUP(C91,sales_teams!A:A,sales_teams!C:C,"") -> Rocco Neubert | F91: =_xlfn.XLOOKUP(C91,sales_teams!A:A,sales_teams!D:D,"") -> East | G91: GTX Plus Basic | H91: =_xlfn.XLOOKUP(G91,products!A:A,products!B:B,"") -> GTX | I91: J-Texon | J91: =_xlfn.XLOOKUP(I91,accounts!A:A,accounts!B:B,"") -> retail | K91: =_xlfn.XLOOKUP(I91,accounts!A:A,accounts!F:F,"") -> Mid-Market | L91: Engaging | N91: TBD | O91: 42698 | Q91: =_xlfn.XLOOKUP(G91,products!A:A,products!C:C,"") -> 1096 | R91: 44 | S91: =Q91*R91 -> 48224
A92: SU8JNMP4 | B92: Retention | C92: Kami Bicknell | D92: =_xlfn.XLOOKUP(C92,sales_teams!A:A,sales_teams!B:B,"") -> W596440 | E92: =_xlfn.XLOOKUP(C92,sales_teams!A:A,sales_teams!C:C,"") -> Summer Sewald | F92: =_xlfn.XLOOKUP(C92,sales_teams!A:A,sales_teams!D:D,"") -> West | G92: GTX Plus Basic | H92: =_xlfn.XLOOKUP(G92,products!A:A,products!B:B,"") -> GTX | I92: Bubba Gump | J92: =_xlfn.XLOOKUP(I92,accounts!A:A,accounts!B:B,"") -> software | K92: =_xlfn.XLOOKUP(I92,accounts!A:A,accounts!F:F,"") -> Mid-Market | L92: Engaging | N92: TBD | O92: 42698 | Q92: =_xlfn.XLOOKUP(G92,products!A:A,products!C:C,"") -> 1096 | R92: 27 | S92: =Q92*R92 -> 29592
A93: V2X2KMUR | B93: Retention | C93: Kami Bicknell | D93: =_xlfn.XLOOKUP(C93,sales_teams!A:A,sales_teams!B:B,"") -> W596440 | E93: =_xlfn.XLOOKUP(C93,sales_teams!A:A,sales_teams!C:C,"") -> Summer Sewald | F93: =_xlfn.XLOOKUP(C93,sales_teams!A:A,sales_teams!D:D,"") -> West | G93: GTX Plus Basic | H93: =_xlfn.XLOOKUP(G93,products!A:A,products!B:B,"") -> GTX | I93: Faxquote | J93: =_xlfn.XLOOKUP(I93,accounts!A:A,accounts!B:B,"") -> telecommunications | K93: =_xlfn.XLOOKUP(I93,accounts!A:A,accounts!F:F,"") -> Enterprise | L93: Won | M93: Executive Relationship | N93: Ivy Green-Tech | O93: 42698 | P93: 42822 | Q93: =_xlfn.XLOOKUP(G93,products!A:A,products!C:C,"") -> 1096 | R93: 2 | S93: =Q93*R93 -> 2192
A94: AJIPJP75 | B94: Expansion | C94: Marty Freudenburg | D94: =_xlfn.XLOOKUP(C94,sales_teams!A:A,sales_teams!B:B,"") -> C234392 | E94: =_xlfn.XLOOKUP(C94,sales_teams!A:A,sales_teams!C:C,"") -> Melvin Marxen | F94: =_xlfn.XLOOKUP(C94,sales_teams!A:A,sales_teams!D:D,"") -> Central | G94: GTX Plus Basic | H94: =_xlfn.XLOOKUP(G94,products!A:A,products!B:B,"") -> GTX | I94: Codehow | J94: =_xlfn.XLOOKUP(I94,accounts!A:A,accounts!B:B,"") -> software | K94: =_xlfn.XLOOKUP(I94,accounts!A:A,accounts!F:F,"") -> Mid-Market | L94: Lost | M94: Feature Requirements | N94: Ivy Green-Tech | O94: 42698 | P94: 42799 | Q94: =_xlfn.XLOOKUP(G94,products!A:A,products!C:C,"") -> 1096 | R94: 10 | S94: =Q94*R94 -> 10960
A95: NYVA2G6U | B95: Expansion | C95: Versie Hillebrand | D95: =_xlfn.XLOOKUP(C95,sales_teams!A:A,sales_teams!B:B,"") -> C234829 | E95: =_xlfn.XLOOKUP(C95,sales_teams!A:A,sales_teams!C:C,"") -> Dustin Brinkmann | F95: =_xlfn.XLOOKUP(C95,sales_teams!A:A,sales_teams!D:D,"") -> Central | G95: MG Special | H95: =_xlfn.XLOOKUP(G95,products!A:A,products!B:B,"") -> MG | I95: Dontechi | J95: =_xlfn.XLOOKUP(I95,accounts!A:A,accounts!B:B,"") -> software | K95: =_xlfn.XLOOKUP(I95,accounts!A:A,accounts!F:F,"") -> Enterprise | L95: Won | M95: Product Superiority | N95: Ivy Green-Tech | O95: 42698 | P95: 42796 | Q95: =_xlfn.XLOOKUP(G95,products!A:A,products!C:C,"") -> 55 | R95: 39 | S95: =Q95*R95 -> 2145
A96: FF45BXTL | B96: Expansion | C96: Vicki Laflamme | D96: =_xlfn.XLOOKUP(C96,sales_teams!A:A,sales_teams!B:B,"") -> W975078 | E96: =_xlfn.XLOOKUP(C96,sales_teams!A:A,sales_teams!C:C,"") -> Celia Rouche | F96: =_xlfn.XLOOKUP(C96,sales_teams!A:A,sales_teams!D:D,"") -> West | G96: MG Advanced | H96: =_xlfn.XLOOKUP(G96,products!A:A,products!B:B,"") -> MG | I96: Konex | J96: =_xlfn.XLOOKUP(I96,accounts!A:A,accounts!B:B,"") -> technolgy | K96: =_xlfn.XLOOKUP(I96,accounts!A:A,accounts!F:F,"") -> Enterprise | L96: Won | M96: Brand Uniqueness | N96: Falconia Enterprises | O96: 42698 | P96: 42821 | Q96: =_xlfn.XLOOKUP(G96,products!A:A,products!C:C,"") -> 3393 | R96: 46 | S96: =Q96*R96 -> 156078
A97: TTA9LYBS | B97: Expansion | C97: Anna Snelling | D97: =_xlfn.XLOOKUP(C97,sales_teams!A:A,sales_teams!B:B,"") -> C265891 | E97: =_xlfn.XLOOKUP(C97,sales_teams!A:A,sales_teams!C:C,"") -> Dustin Brinkmann | F97: =_xlfn.XLOOKUP(C97,sales_teams!A:A,sales_teams!D:D,"") -> Central | G97: MG Special | H97: =_xlfn.XLOOKUP(G97,products!A:A,products!B:B,"") -> MG | I97: Treequote | J97: =_xlfn.XLOOKUP(I97,accounts!A:A,accounts!B:B,"") -> telecommunications | K97: =_xlfn.XLOOKUP(I97,accounts!A:A,accounts!F:F,"") -> Enterprise | L97: Won | M97: Executive Relationship | N97: Enigma Analytics | O97: 42699 | P97: 42795 | Q97: =_xlfn.XLOOKUP(G97,products!A:A,products!C:C,"") -> 55 | R97: 1 | S97: =Q97*R97 -> 55
A98: PAGZQH8L | B98: Retention | C98: Cecily Lampkin | D98: =_xlfn.XLOOKUP(C98,sales_teams!A:A,sales_teams!B:B,"") -> C163925 | E98: =_xlfn.XLOOKUP(C98,sales_teams!A:A,sales_teams!C:C,"") -> Dustin Brinkmann | F98: =_xlfn.XLOOKUP(C98,sales_teams!A:A,sales_teams!D:D,"") -> Central | G98: MG Advanced | H98: =_xlfn.XLOOKUP(G98,products!A:A,products!B:B,"") -> MG | I98: Treequote | J98: =_xlfn.XLOOKUP(I98,accounts!A:A,accounts!B:B,"") -> telecommunications | K98: =_xlfn.XLOOKUP(I98,accounts!A:A,accounts!F:F,"") -> Enterprise | L98: Won | M98: Strategic Timing | N98: Enigma Analytics | O98: 42699 | P98: 42800 | Q98: =_xlfn.XLOOKUP(G98,products!A:A,products!C:C,"") -> 3393 | R98: 8 | S98: =Q98*R98 -> 27144
A99: J7YF6DS7 | B99: Retention | C99: Corliss Cosme | D99: =_xlfn.XLOOKUP(C99,sales_teams!A:A,sales_teams!B:B,"") -> E500449 | E99: =_xlfn.XLOOKUP(C99,sales_teams!A:A,sales_teams!C:C,"") -> Cara Losch | F99: =_xlfn.XLOOKUP(C99,sales_teams!A:A,sales_teams!D:D,"") -> East | G99: GTX Plus Pro | H99: =_xlfn.XLOOKUP(G99,products!A:A,products!B:B,"") -> GTX | I99: Betasoloin | J99: =_xlfn.XLOOKUP(I99,accounts!A:A,accounts!B:B,"") -> medical | K99: =_xlfn.XLOOKUP(I99,accounts!A:A,accounts!F:F,"") -> SMB | L99: Won | M99: Advanced Technology | N99: Cobblepot Exports | O99: 42699 | P99: 42795 | Q99: =_xlfn.XLOOKUP(G99,products!A:A,products!C:C,"") -> 5482 | R99: 28 | S99: =Q99*R99 -> 153496
A100: S5IXY4Z9 | B100: Diversification | C100: Corliss Cosme | D100: =_xlfn.XLOOKUP(C100,sales_teams!A:A,sales_teams!B:B,"") -> E500449 | E100: =_xlfn.XLOOKUP(C100,sales_teams!A:A,sales_teams!C:C,"") -> Cara Losch | F100: =_xlfn.XLOOKUP(C100,sales_teams!A:A,sales_teams!D:D,"") -> East | G100: GTX Pro | H100: =_xlfn.XLOOKUP(G100,products!A:A,products!B:B,"") -> GTX | I100: Betasoloin | J100: =_xlfn.XLOOKUP(I100,accounts!A:A,accounts!B:B,"") -> medical | K100: =_xlfn.XLOOKUP(I100,accounts!A:A,accounts!F:F,"") -> SMB | L100: Won | M100: Advanced Technology | N100: Ivy Green-Tech | O100: 42699 | P100: 42800 | Q100: =_xlfn.XLOOKUP(G100,products!A:A,products!C:C,"") -> 4821 | R100: 48 | S100: =Q100*R100 -> 231408
A101: JQBJMETQ | B101: Expansion | C101: Darcel Schlecht | D101: =_xlfn.XLOOKUP(C101,sales_teams!A:A,sales_teams!B:B,"") -> C486814 | E101: =_xlfn.XLOOKUP(C101,sales_teams!A:A,sales_teams!C:C,"") -> Melvin Marxen | F101: =_xlfn.XLOOKUP(C101,sales_teams!A:A,sales_teams!D:D,"") -> Central | G101: MG Special | H101: =_xlfn.XLOOKUP(G101,products!A:A,products!B:B,"") -> MG | I101: Domzoom | J101: =_xlfn.XLOOKUP(I101,accounts!A:A,accounts!B:B,"") -> entertainment | K101: =_xlfn.XLOOKUP(I101,accounts!A:A,accounts!F:F,"") -> SMB | L101: Won | M101: Product Superiority | N101: Falconia Enterprises | O101: 42699 | P101: 42821 | Q101: =_xlfn.XLOOKUP(G101,products!A:A,products!C:C,"") -> 55 | R101: 24 | S101: =Q101*R101 -> 1320
A102: 0LVWSWEW | B102: Retention | C102: Violet Mclelland | D102: =_xlfn.XLOOKUP(C102,sales_teams!A:A,sales_teams!B:B,"") -> E152967 | E102: =_xlfn.XLOOKUP(C102,sales_teams!A:A,sales_teams!C:C,"") -> Cara Losch | F102: =_xlfn.XLOOKUP(C102,sales_teams!A:A,sales_teams!D:D,"") -> East | G102: MG Special | H102: =_xlfn.XLOOKUP(G102,products!A:A,products!B:B,"") -> MG | I102: Donquadtech | J102: =_xlfn.XLOOKUP(I102,accounts!A:A,accounts!B:B,"") -> technolgy | K102: =_xlfn.XLOOKUP(I102,accounts!A:A,accounts!F:F,"") -> Mid-Market | L102: Won | M102: Product Superiority | N102: Falconia Enterprises | O102: 42699 | P102: 42800 | Q102: =_xlfn.XLOOKUP(G102,products!A:A,products!C:C,"") -> 55 | R102: 40 | S102: =Q102*R102 -> 2200
A103: K53BC1T9 | B103: Retention | C103: Anna Snelling | D103: =_xlfn.XLOOKUP(C103,sales_teams!A:A,sales_teams!B:B,"") -> C265891 | E103: =_xlfn.XLOOKUP(C103,sales_teams!A:A,sales_teams!C:C,"") -> Dustin Brinkmann | F103: =_xlfn.XLOOKUP(C103,sales_teams!A:A,sales_teams!D:D,"") -> Central | G103: MG Special | H103: =_xlfn.XLOOKUP(G103,products!A:A,products!B:B,"") -> MG | I103: Domzoom | J103: =_xlfn.XLOOKUP(I103,accounts!A:A,accounts!B:B,"") -> entertainment | K103: =_xlfn.XLOOKUP(I103,accounts!A:A,accounts!F:F,"") -> SMB | L103: Lost | M103: Competitor Selection | N103: Cobblepot Exports | O103: 42700 | P103: 42821 | Q103: =_xlfn.XLOOKUP(G103,products!A:A,products!C:C,"") -> 55 | R103: 24 | S103: =Q103*R103 -> 1320
A104: D40N5I9Y | B104: Diversification | C104: Darcel Schlecht | D104: =_xlfn.XLOOKUP(C104,sales_teams!A:A,sales_teams!B:B,"") -> C486814 | E104: =_xlfn.XLOOKUP(C104,sales_teams!A:A,sales_teams!C:C,"") -> Melvin Marxen | F104: =_xlfn.XLOOKUP(C104,sales_teams!A:A,sales_teams!D:D,"") -> Central | G104: GTX Pro | H104: =_xlfn.XLOOKUP(G104,products!A:A,products!B:B,"") -> GTX | I104: Finhigh | J104: =_xlfn.XLOOKUP(I104,accounts!A:A,accounts!B:B,"") -> finance | K104: =_xlfn.XLOOKUP(I104,accounts!A:A,accounts!F:F,"") -> Mid-Market | L104: Won | M104: Brand Uniqueness | N104: Cobblepot Exports | O104: 42700 | P104: 42802 | Q104: =_xlfn.XLOOKUP(G104,products!A:A,products!C:C,"") -> 4821 | R104: 29 | S104: =Q104*R104 -> 139809
... A108: UK0LEZRJ | B108: Expansion | C108: Kary Hendrixson | D108: =_xlfn.XLOOKUP(C108,sales_teams!A:A,sales_teams!B:B,"") -> W674591 | E108: =_xlfn.XLOOKUP(C108,sales_teams!A:A,sales_teams!C:C,"") -> Summer Sewald | F108: =_xlfn.XLOOKUP(C108,sales_teams!A:A,sales_teams!D:D,"") -> West | G108: GTX Basic | H108: =_xlfn.XLOOKUP(G108,products!A:A,products!B:B,"") -> GTX | I108: Condax | J108: =_xlfn.XLOOKUP(I108,accounts!A:A,accounts!B:B,"") -> medical | K108: =_xlfn.XLOOKUP(I108,accounts!A:A,accounts!F:F,"") -> SMB | L108: Won | M108: Executive Relationship | N108: Enigma Analytics | O108: 42701 | P108: 42797 | Q108: =_xlfn.XLOOKUP(G108,products!A:A,products!C:C,"") -> 550 | R108: 22 | S108: =Q108*R108 -> 12100
A109: PFFHM7HR | B109: Diversification | C109: Markita Hansen | D109: =_xlfn.XLOOKUP(C109,sales_teams!A:A,sales_teams!B:B,"") -> W337844 | E109: =_xlfn.XLOOKUP(C109,sales_teams!A:A,sales_teams!C:C,"") -> Celia Rouche | F109: =_xlfn.XLOOKUP(C109,sales_teams!A:A,sales_teams!D:D,"") -> West | G109: MG Advanced | H109: =_xlfn.XLOOKUP(G109,products!A:A,products!B:B,"") -> MG | I109: Opentech | J109: =_xlfn.XLOOKUP(I109,accounts!A:A,accounts!B:B,"") -> finance | K109: =_xlfn.XLOOKUP(I109,accounts!A:A,accounts!F:F,"") -> SMB | L109: Engaging | N109: TBD | O109: 42701 | Q109: =_xlfn.XLOOKUP(G109,products!A:A,products!C:C,"") -> 3393 | R109: 10 | S109: =Q109*R109 -> 33930
...

Sheet sales_teams
A1: sales_agent | B1: sales_agent_id | C1: manager | D1: regional_office
A2: Anna Snelling | B2: C265891 | C2: Dustin Brinkmann | D2: Central
A3: Cecily Lampkin | B3: C163925 | C3: Dustin Brinkmann | D3: Central
A4: Versie Hillebrand | B4: C234829 | C4: Dustin Brinkmann | D4: Central
A5: Lajuana Vencill | B5: C100201 | C5: Dustin Brinkmann | D5: Central
A6: Moses Frase | B6: C62195 | C6: Dustin Brinkmann | D6: Central
A7: Jonathan Berthelot | B7: C309699 | C7: Melvin Marxen | D7: Central
A8: Marty Freudenburg | B8: C234392 | C8: Melvin Marxen | D8: Central
A9: Gladys Colclough | B9: C130664 | C9: Melvin Marxen | D9: Central
A10: Niesha Huffines | B10: C961860 | C10: Melvin Marxen | D10: Central
A11: Darcel Schlecht | B11: C486814 | C11: Melvin Marxen | D11: Central
A12: Mei-Mei Johns | B12: C42503 | C12: Melvin Marxen | D12: Central
... A36: Carl Lin | B36: W324849 | C36: Summer Sewald | D36: West

Sheet products
A1: product | B1: series | C1: sales_price
A2: GTX Basic | B2: GTX | C2: 550
A3: GTX Pro | B3: GTX | C3: 4821
A4: MG Special | B4: MG | C4: 55
A5: MG Advanced | B5: MG | C5: 3393
A6: GTX Plus Pro | B6: GTX | C6: 5482
A7: GTX Plus Basic | B7: GTX | C7: 1096
A8: GTK 500 | B8: GTK | C8: 26768

Sheet accounts
A1: account | B1: sector | C1: year_established | D1: revenue | E1: employees | F1: account_tier | G1: office_location
A2: Acme Corporation | B2: technolgy | C2: 1996 | D2: =SUMIFS(sales_pipeline!S:S, sales_pipeline!I:I, A2, sales_pipeline!L:L, "Won") -> 2530983 | E2: 2822 | F2: {=_xlfn.IFS(E2<1000, "SMB", E2<=5000, "Mid-Market", E2>5000, "Enterprise")} -> Mid-Market | G2: United States
A3: Betasoloin | B3: medical | C3: 1999 | D3: =SUMIFS(sales_pipeline!S:S, sales_pipeline!I:I, A3, sales_pipeline!L:L, "Won") -> 2399963 | E3: 495 | F3: {=_xlfn.IFS(E3<1000, "SMB", E3<=5000, "Mid-Market", E3>5000, "Enterprise")} -> SMB | G3: United States
A4: Betatech | B4: medical | C4: 1986 | D4: =SUMIFS(sales_pipeline!S:S, sales_pipeline!I:I, A4, sales_pipeline!L:L, "Won") -> 2459593 | E4: 1185 | F4: {=_xlfn.IFS(E4<1000, "SMB", E4<=5000, "Mid-Market", E4>5000, "Enterprise")} -> Mid-Market | G4: Kenya
A5: Bioholding | B5: medical | C5: 2012 | D5: =SUMIFS(sales_pipeline!S:S, sales_pipeline!I:I, A5, sales_pipeline!L:L, "Won") -> 2419653 | E5: 1356 | F5: {=_xlfn.IFS(E5<1000, "SMB", E5<=5000, "Mid-Market", E5>5000, "Enterprise")} -> Mid-Market | G5: Philipines
A6: Bioplex | B6: medical | C6: 1991 | D6: =SUMIFS(sales_pipeline!S:S, sales_pipeline!I:I, A6, sales_pipeline!L:L, "Won") -> 1759072 | E6: 1016 | F6: {=_xlfn.IFS(E6<1000, "SMB", E6<=5000, "Mid-Market", E6>5000, "Enterprise")} -> Mid-Market | G6: United States
A7: Blackzim | B7: retail | C7: 2009 | D7: =SUMIFS(sales_pipeline!S:S, sales_pipeline!I:I, A7, sales_pipeline!L:L, "Won") -> 1938216 | E7: 1588 | F7: {=_xlfn.IFS(E7<1000, "SMB", E7<=5000, "Mid-Market", E7>5000, "Enterprise")} -> Mid-Market | G7: United States
A8: Bluth Company | B8: technolgy | C8: 1993 | D8: =SUMIFS(sales_pipeline!S:S, sales_pipeline!I:I, A8, sales_pipeline!L:L, "Won") -> 1474886 | E8: 3027 | F8: {=_xlfn.IFS(E8<1000, "SMB", E8<=5000, "Mid-Market", E8>5000, "Enterprise")} -> Mid-Market | G8: United States
A9: Bubba Gump | B9: software | C9: 2002 | D9: =SUMIFS(sales_pipeline!S:S, sales_pipeline!I:I, A9, sales_pipeline!L:L, "Won") -> 2405614 | E9: 2253 | F9: {=_xlfn.IFS(E9<1000, "SMB", E9<=5000, "Mid-Market", E9>5000, "Enterprise")} -> Mid-Market | G9: United States
A10: Cancity | B10: retail | C10: 2001 | D10: =SUMIFS(sales_pipeline!S:S, sales_pipeline!I:I, A10, sales_pipeline!L:L, "Won") -> 2918715 | E10: 2448 | F10: {=_xlfn.IFS(E10<1000, "SMB", E10<=5000, "Mid-Market", E10>5000, "Enterprise")} -> Mid-Market | G10: United States
A11: Cheers | B11: entertainment | C11: 1993 | D11: =SUMIFS(sales_pipeline!S:S, sales_pipeline!I:I, A11, sales_pipeline!L:L, "Won") -> 5492763 | E11: 6472 | F11: {=_xlfn.IFS(E11<1000, "SMB", E11<=5000, "Mid-Market", E11>5000, "Enterprise")} -> Enterprise | G11: United States
A12: Codehow | B12: software | C12: 1998 | D12: =SUMIFS(sales_pipeline!S:S, sales_pipeline!I:I, A12, sales_pipeline!L:L, "Won") -> 3562106 | E12: 2641 | F12: {=_xlfn.IFS(E12<1000, "SMB", E12<=5000, "Mid-Market", E12>5000, "Enterprise")} -> Mid-Market | G12: United States
A13: Condax | B13: medical | C13: 2017 | D13: =SUMIFS(sales_pipeline!S:S, sales_pipeline!I:I, A13, sales_pipeline!L:L, "Won") -> 5099812 | E13: 9 | F13: {=_xlfn.IFS(E13<1000, "SMB", E13<=5000, "Mid-Market", E13>5000, "Enterprise")} -> SMB | G13: United States
... A86: Zumgoity | B86: medical | C86: 1984 | D86: =SUMIFS(sales_pipeline!S:S, sales_pipeline!I:I, A86, sales_pipeline!L:L, "Won") -> 2075752 | E86: 1210 | F86: {=_xlfn.IFS(E86<1000, "SMB", E86<=5000, "Mid-Market", E86>5000, "Enterprise")} -> Mid-Market | G86: United States
